Workbook
Name Year: 'Setup'!$C$6
Name Categories: 'Setup'!$E$10:$E$39

Sheet Start here
B2: Clear Budget
B3: Monthly budget, paycheck plan, bills, debt and savings for Google Sheets and Excel
C4: Start here | D4: Dashboard | E4: Setup | F4: Months | G4: Bills | H4: Paycheck | I4: Debt | J4: Savings
B6: 1 | C6: Open it in your app | D6: Download the file from Etsy.com > Purchases on a computer (the Etsy phone app cannot download files) and save it; do not open it in a browser preview. Google Sheets: on drive.google.com choose New > File upload, pick the .xlsx, then open it with Google Sheets. Excel: double-click the file. There is no link to request and no access to wait for. | T6: January | U6: =SUMPRODUCT(('January'!$E$7:$E$86<>"")*('January'!$D$7:$D$86<>"")*(COUNTIF(Categories,'January'!$D$7:$D$86)=0)) | V6: =SUMPRODUCT(('January'!$E$7:$E$86<>"")*('January'!$D$7:$D$86="")) | W6: =IF(U6>0,1,0)
B7: 2 | C7: Look at January, then clear it | D7: January holds an example month so you can see the math work. Select the shaded Date to Amount cells in January's log and press Delete. The Ready check below shows Done when it is gone. | T7: February | U7: =SUMPRODUCT(('February'!$E$7:$E$86<>"")*('February'!$D$7:$D$86<>"")*(COUNTIF(Categories,'February'!$D$7:$D$86)=0)) | V7: =SUMPRODUCT(('February'!$E$7:$E$86<>"")*('February'!$D$7:$D$86="")) | W7: =IF(U7>0,1,0)
B8: 3 | C8: Fill in Setup once | D8: Type your take-home pay, then name your own categories, pick a group for each and give each a monthly budget. Aim for Left to budget = 0. Change or add categories any time; every tab follows. | T8: March | U8: =SUMPRODUCT(('March'!$E$7:$E$86<>"")*('March'!$D$7:$D$86<>"")*(COUNTIF(Categories,'March'!$D$7:$D$86)=0)) | V8: =SUMPRODUCT(('March'!$E$7:$E$86<>"")*('March'!$D$7:$D$86="")) | W8: =IF(U8>0,1,0)
B9: 4 | C9: Log spending in this month | D9: Pick this month in the jump row below. Starting mid-year? Empty months stay out of your totals. Starting now, before the new year? Set the Year in Setup to this year and use October, November and December; in January keep that copy as last year's record and start this year in a fresh download, copying your Setup categories across. | T9: April | U9: =SUMPRODUCT(('April'!$E$7:$E$86<>"")*('April'!$D$7:$D$86<>"")*(COUNTIF(Categories,'April'!$D$7:$D$86)=0)) | V9: =SUMPRODUCT(('April'!$E$7:$E$86<>"")*('April'!$D$7:$D$86="")) | W9: =IF(U9>0,1,0)
B10: 5 | C10: Check your Dashboard | D10: See the year by month and where the money went. Bills, Paycheck plan, Debt and Savings are extras: use them when you want them, skip them if you do not. | T10: May | U10: =SUMPRODUCT(('May'!$E$7:$E$86<>"")*('May'!$D$7:$D$86<>"")*(COUNTIF(Categories,'May'!$D$7:$D$86)=0)) | V10: =SUMPRODUCT(('May'!$E$7:$E$86<>"")*('May'!$D$7:$D$86="")) | W10: =IF(U10>0,1,0)
T11: June | U11: =SUMPRODUCT(('June'!$E$7:$E$86<>"")*('June'!$D$7:$D$86<>"")*(COUNTIF(Categories,'June'!$D$7:$D$86)=0)) | V11: =SUMPRODUCT(('June'!$E$7:$E$86<>"")*('June'!$D$7:$D$86="")) | W11: =IF(U11>0,1,0)
C12: Ready check | E12: Updates as you type. | T12: July | U12: =SUMPRODUCT(('July'!$E$7:$E$86<>"")*('July'!$D$7:$D$86<>"")*(COUNTIF(Categories,'July'!$D$7:$D$86)=0)) | V12: =SUMPRODUCT(('July'!$E$7:$E$86<>"")*('July'!$D$7:$D$86="")) | W12: =IF(U12>0,1,0)
C13: Check | D13: Status | E13: What to do | T13: August | U13: =SUMPRODUCT(('August'!$E$7:$E$86<>"")*('August'!$D$7:$D$86<>"")*(COUNTIF(Categories,'August'!$D$7:$D$86)=0)) | V13: =SUMPRODUCT(('August'!$E$7:$E$86<>"")*('August'!$D$7:$D$86="")) | W13: =IF(U13>0,1,0)
C14: Income entered | D14: =IF('Setup'!$C$18>0,"Done","To do") | E14: =IF('Setup'!$C$18>0,"","Add your take-home pay in Setup") | T14: September | U14: =SUMPRODUCT(('September'!$E$7:$E$86<>"")*('September'!$D$7:$D$86<>"")*(COUNTIF(Categories,'September'!$D$7:$D$86)=0)) | V14: =SUMPRODUCT(('September'!$E$7:$E$86<>"")*('September'!$D$7:$D$86="")) | W14: =IF(U14>0,1,0)
C15: Every dollar has a job | D15: =IF(ROUND('Setup'!$G$41,2)=0,"Done","To do") | E15: =IF(ROUND('Setup'!$G$41,2)>0,"You have "&TEXT('Setup'!$G$41,"$#,##0.00")&" not budgeted yet",IF(ROUND('Setup'!$G$41,2)<0,"Over by "&TEXT(-'Setup'!$G$41,"$#,##0.00")&": lower a budget","")) | T15: October | U15: =SUMPRODUCT(('October'!$E$7:$E$86<>"")*('October'!$D$7:$D$86<>"")*(COUNTIF(Categories,'October'!$D$7:$D$86)=0)) | V15: =SUMPRODUCT(('October'!$E$7:$E$86<>"")*('October'!$D$7:$D$86="")) | W15: =IF(U15>0,1,0)
C16: Every category has a group | D16: =IF(COUNTIFS('Setup'!$E$10:$E$39,"<>",'Setup'!$F$10:$F$39,"")=0,"Done","To do") | E16: =IF(COUNTIFS('Setup'!$E$10:$E$39,"<>",'Setup'!$F$10:$F$39,"")=0,"",COUNTIFS('Setup'!$E$10:$E$39,"<>",'Setup'!$F$10:$F$39,"")&" categories need a group: pick Needs, Wants, Savings or Debt in Setup") | T16: November | U16: =SUMPRODUCT(('November'!$E$7:$E$86<>"")*('November'!$D$7:$D$86<>"")*(COUNTIF(Categories,'November'!$D$7:$D$86)=0)) | V16: =SUMPRODUCT(('November'!$E$7:$E$86<>"")*('November'!$D$7:$D$86="")) | W16: =IF(U16>0,1,0)
C17: Spending matches your categories | D17: =IF(SUM(U6:U17)=0,"Done","To do") | E17: =IF(SUM(U6:U17)=0,"",SUM(U6:U17)&" entries use a category not in Setup (first in "&INDEX(T6:T17,MATCH(1,W6:W17,0))&"): pick their category again") | T17: December | U17: =SUMPRODUCT(('December'!$E$7:$E$86<>"")*('December'!$D$7:$D$86<>"")*(COUNTIF(Categories,'December'!$D$7:$D$86)=0)) | V17: =SUMPRODUCT(('December'!$E$7:$E$86<>"")*('December'!$D$7:$D$86="")) | W17: =IF(U17>0,1,0)
C18: No amounts without a category | D18: =IF(SUM(V6:V17)=0,"Done","To do") | E18: =IF(SUM(V6:V17)=0,"",SUM(V6:V17)&" amounts have no category, so they are not counted yet")
C19: Example cleared | D19: =IF((COUNTIFS('January'!$B$7:$B$86,DATE(2027,1,3),'January'!$C$7:$C$86,"Rent",'January'!$E$7:$E$86,1200)+COUNTIFS('January'!$B$7:$B$86,DATE(2027,1,4),'January'!$C$7:$C$86,"Weekly shop",'January'!$E$7:$E$86,112.4)+COUNTIFS('January'!$B$7:$B$86,DATE(2027,1,6),'January'!$C$7:$C$86,"Bus pass",'January'!$E$7:$E$86,60)+COUNTIFS('January'!$B$7:$B$86,DATE(2027,1,9),'January'!$C$7:$C$86,"Pizza night",'January'!$E$7:$E$86,38.5)+COUNTIFS('January'!$B$7:$B$86,DATE(2027,1,11),'January'!$C$7:$C$86,"Weekly shop",'January'!$E$7:$E$86,96.2)+COUNTIFS('January'!$B$7:$B$86,DATE(2027,1,14),'January'!$C$7:$C$86,"Phone bill",'January'!$E$7:$E$86,55)+COUNTIFS('January'!$B$7:$B$86,DATE(2027,1,15),'January'!$C$7:$C$86,"To emergency fund",'January'!$E$7:$E$86,200)+COUNTIFS('January'!$B$7:$B$86,DATE(2027,1,18),'January'!$C$7:$C$86,"Streaming",'January'!$E$7:$E$86,15.99)+COUNTIFS('January'!$B$7:$B$86,DATE(2027,1,21),'January'!$C$7:$C$86,"Card payment",'January'!$E$7:$E$86,150)+COUNTIFS('January'!$B$7:$B$86,DATE(2027,1,24),'January'!$C$7:$C$86,"Concert tickets",'January'!$E$7:$E$86,120)+COUNTIFS('January'!$B$7:$B$86,DATE(2027,1,25),'January'!$C$7:$C$86,"Shoes",'January'!$E$7:$E$86,64))=0,"Done","To do") | E19: =IF((COUNTIFS('January'!$B$7:$B$86,DATE(2027,1,3),'January'!$C$7:$C$86,"Rent",'January'!$E$7:$E$86,1200)+COUNTIFS('January'!$B$7:$B$86,DATE(2027,1,4),'January'!$C$7:$C$86,"Weekly shop",'January'!$E$7:$E$86,112.4)+COUNTIFS('January'!$B$7:$B$86,DATE(2027,1,6),'January'!$C$7:$C$86,"Bus pass",'January'!$E$7:$E$86,60)+COUNTIFS('January'!$B$7:$B$86,DATE(2027,1,9),'January'!$C$7:$C$86,"Pizza night",'January'!$E$7:$E$86,38.5)+COUNTIFS('January'!$B$7:$B$86,DATE(2027,1,11),'January'!$C$7:$C$86,"Weekly shop",'January'!$E$7:$E$86,96.2)+COUNTIFS('January'!$B$7:$B$86,DATE(2027,1,14),'January'!$C$7:$C$86,"Phone bill",'January'!$E$7:$E$86,55)+COUNTIFS('January'!$B$7:$B$86,DATE(2027,1,15),'January'!$C$7:$C$86,"To emergency fund",'January'!$E$7:$E$86,200)+COUNTIFS('January'!$B$7:$B$86,DATE(2027,1,18),'January'!$C$7:$C$86,"Streaming",'January'!$E$7:$E$86,15.99)+COUNTIFS('January'!$B$7:$B$86,DATE(2027,1,21),'January'!$C$7:$C$86,"Card payment",'January'!$E$7:$E$86,150)+COUNTIFS('January'!$B$7:$B$86,DATE(2027,1,24),'January'!$C$7:$C$86,"Concert tickets",'January'!$E$7:$E$86,120)+COUNTIFS('January'!$B$7:$B$86,DATE(2027,1,25),'January'!$C$7:$C$86,"Shoes",'January'!$E$7:$E$86,64))=0,"","Clear the example in January (step 2)")
C20: Your split (info, not pass or fail) | D20: Info | E20: =IF('Setup'!$G$40=0,"",TEXT(SUMIF('Setup'!$F$10:$F$39,"Needs",'Setup'!$G$10:$G$39)/'Setup'!$G$40,"0%")&" needs, "&TEXT(SUMIF('Setup'!$F$10:$F$39,"Wants",'Setup'!$G$10:$G$39)/'Setup'!$G$40,"0%")&" wants, "&TEXT((SUMIF('Setup'!$F$10:$F$39,"Savings",'Setup'!$G$10:$G$39)+SUMIF('Setup'!$F$10:$F$39,"Debt",'Setup'!$G$10:$G$39))/'Setup'!$G$40,"0%")&" savings and debt (50/30/20 guide)")
C22: Jump to a month
C23: January | D23: February | E23: March
C24: April | D24: May | E24: June
C25: July | D25: August | E25: September
C26: October | D26: November | E26: December
C28: If something looks wrong
C29: A month total looks too low: check the Ready check for amounts without a category or with a category not in Setup.
C30: A category is missing from the dropdown: add it in Setup (any empty row); it appears in every month.
C31: I typed over a formula: Edit > Undo, or File > Version history in Google Sheets.
C32: Amounts show $ but I use another currency: unprotect the tab (no password) and change the number format.
C34: Colour key
C35: Type here | E35: Shaded cells are yours to fill in.
C36: Calculated | E36: Plain cells hold formulas.
C38: Tip | D38: Shaded cells are for typing. Plain cells hold formulas. In Excel they are locked; to change one use Review > Unprotect Sheet (there is no password). In Google Sheets, if you type over a formula, Edit > Undo or File > Version history brings it back.

Sheet Dashboard
B2: Dashboard
B3: Your year at a glance. Nothing to type here.
B4: Start here | C4: Dashboard | D4: Setup | E4: Months | F4: Bills | G4: Paycheck | H4: Debt | I4: Savings
B6: Month | C6: Income | D6: Spent | E6: Left over | F6: Saved and debt paid | H6: Category | I6: Spent this year
B7: January | C7: =IF(COUNT('January'!$E$7:$E$86)>0,'January'!H6,"") | D7: =IF(COUNT('January'!$E$7:$E$86)>0,'January'!H7,"") | E7: =IF(COUNT('January'!$E$7:$E$86)>0,'January'!H8,"") | F7: =IF(COUNT('January'!$E$7:$E$86)>0,'January'!H9,"") | H7: =IF('Setup'!E10="","",'Setup'!E10) | I7: =IF(H7="","",SUMIFS('January'!$E$7:$E$86,'January'!$D$7:$D$86,H7)+SUMIFS('February'!$E$7:$E$86,'February'!$D$7:$D$86,H7)+SUMIFS('March'!$E$7:$E$86,'March'!$D$7:$D$86,H7)+SUMIFS('April'!$E$7:$E$86,'April'!$D$7:$D$86,H7)+SUMIFS('May'!$E$7:$E$86,'May'!$D$7:$D$86,H7)+SUMIFS('June'!$E$7:$E$86,'June'!$D$7:$D$86,H7)+SUMIFS('July'!$E$7:$E$86,'July'!$D$7:$D$86,H7)+SUMIFS('August'!$E$7:$E$86,'August'!$D$7:$D$86,H7)+SUMIFS('September'!$E$7:$E$86,'September'!$D$7:$D$86,H7)+SUMIFS('October'!$E$7:$E$86,'October'!$D$7:$D$86,H7)+SUMIFS('November'!$E$7:$E$86,'November'!$D$7:$D$86,H7)+SUMIFS('December'!$E$7:$E$86,'December'!$D$7:$D$86,H7)) | J7: =IF(H7="","",'Setup'!F10)
B8: February | C8: =IF(COUNT('February'!$E$7:$E$86)>0,'February'!H6,"") | D8: =IF(COUNT('February'!$E$7:$E$86)>0,'February'!H7,"") | E8: =IF(COUNT('February'!$E$7:$E$86)>0,'February'!H8,"") | F8: =IF(COUNT('February'!$E$7:$E$86)>0,'February'!H9,"") | H8: =IF('Setup'!E11="","",'Setup'!E11) | I8: =IF(H8="","",SUMIFS('January'!$E$7:$E$86,'January'!$D$7:$D$86,H8)+SUMIFS('February'!$E$7:$E$86,'February'!$D$7:$D$86,H8)+SUMIFS('March'!$E$7:$E$86,'March'!$D$7:$D$86,H8)+SUMIFS('April'!$E$7:$E$86,'April'!$D$7:$D$86,H8)+SUMIFS('May'!$E$7:$E$86,'May'!$D$7:$D$86,H8)+SUMIFS('June'!$E$7:$E$86,'June'!$D$7:$D$86,H8)+SUMIFS('July'!$E$7:$E$86,'July'!$D$7:$D$86,H8)+SUMIFS('August'!$E$7:$E$86,'August'!$D$7:$D$86,H8)+SUMIFS('September'!$E$7:$E$86,'September'!$D$7:$D$86,H8)+SUMIFS('October'!$E$7:$E$86,'October'!$D$7:$D$86,H8)+SUMIFS('November'!$E$7:$E$86,'November'!$D$7:$D$86,H8)+SUMIFS('December'!$E$7:$E$86,'December'!$D$7:$D$86,H8)) | J8: =IF(H8="","",'Setup'!F11)
B9: March | C9: =IF(COUNT('March'!$E$7:$E$86)>0,'March'!H6,"") | D9: =IF(COUNT('March'!$E$7:$E$86)>0,'March'!H7,"") | E9: =IF(COUNT('March'!$E$7:$E$86)>0,'March'!H8,"") | F9: =IF(COUNT('March'!$E$7:$E$86)>0,'March'!H9,"") | H9: =IF('Setup'!E12="","",'Setup'!E12) | I9: =IF(H9="","",SUMIFS('January'!$E$7:$E$86,'January'!$D$7:$D$86,H9)+SUMIFS('February'!$E$7:$E$86,'February'!$D$7:$D$86,H9)+SUMIFS('March'!$E$7:$E$86,'March'!$D$7:$D$86,H9)+SUMIFS('April'!$E$7:$E$86,'April'!$D$7:$D$86,H9)+SUMIFS('May'!$E$7:$E$86,'May'!$D$7:$D$86,H9)+SUMIFS('June'!$E$7:$E$86,'June'!$D$7:$D$86,H9)+SUMIFS('July'!$E$7:$E$86,'July'!$D$7:$D$86,H9)+SUMIFS('August'!$E$7:$E$86,'August'!$D$7:$D$86,H9)+SUMIFS('September'!$E$7:$E$86,'September'!$D$7:$D$86,H9)+SUMIFS('October'!$E$7:$E$86,'October'!$D$7:$D$86,H9)+SUMIFS('November'!$E$7:$E$86,'November'!$D$7:$D$86,H9)+SUMIFS('December'!$E$7:$E$86,'December'!$D$7:$D$86,H9)) | J9: =IF(H9="","",'Setup'!F12)
B10: April | C10: =IF(COUNT('April'!$E$7:$E$86)>0,'April'!H6,"") | D10: =IF(COUNT('April'!$E$7:$E$86)>0,'April'!H7,"") | E10: =IF(COUNT('April'!$E$7:$E$86)>0,'April'!H8,"") | F10: =IF(COUNT('April'!$E$7:$E$86)>0,'April'!H9,"") | H10: =IF('Setup'!E13="","",'Setup'!E13) | I10: =IF(H10="","",SUMIFS('January'!$E$7:$E$86,'January'!$D$7:$D$86,H10)+SUMIFS('February'!$E$7:$E$86,'February'!$D$7:$D$86,H10)+SUMIFS('March'!$E$7:$E$86,'March'!$D$7:$D$86,H10)+SUMIFS('April'!$E$7:$E$86,'April'!$D$7:$D$86,H10)+SUMIFS('May'!$E$7:$E$86,'May'!$D$7:$D$86,H10)+SUMIFS('June'!$E$7:$E$86,'June'!$D$7:$D$86,H10)+SUMIFS('July'!$E$7:$E$86,'July'!$D$7:$D$86,H10)+SUMIFS('August'!$E$7:$E$86,'August'!$D$7:$D$86,H10)+SUMIFS('September'!$E$7:$E$86,'September'!$D$7:$D$86,H10)+SUMIFS('October'!$E$7:$E$86,'October'!$D$7:$D$86,H10)+SUMIFS('November'!$E$7:$E$86,'November'!$D$7:$D$86,H10)+SUMIFS('December'!$E$7:$E$86,'December'!$D$7:$D$86,H10)) | J10: =IF(H10="","",'Setup'!F13)
B11: May | C11: =IF(COUNT('May'!$E$7:$E$86)>0,'May'!H6,"") | D11: =IF(COUNT('May'!$E$7:$E$86)>0,'May'!H7,"") | E11: =IF(COUNT('May'!$E$7:$E$86)>0,'May'!H8,"") | F11: =IF(COUNT('May'!$E$7:$E$86)>0,'May'!H9,"") | H11: =IF('Setup'!E14="","",'Setup'!E14) | I11: =IF(H11="","",SUMIFS('January'!$E$7:$E$86,'January'!$D$7:$D$86,H11)+SUMIFS('February'!$E$7:$E$86,'February'!$D$7:$D$86,H11)+SUMIFS('March'!$E$7:$E$86,'March'!$D$7:$D$86,H11)+SUMIFS('April'!$E$7:$E$86,'April'!$D$7:$D$86,H11)+SUMIFS('May'!$E$7:$E$86,'May'!$D$7:$D$86,H11)+SUMIFS('June'!$E$7:$E$86,'June'!$D$7:$D$86,H11)+SUMIFS('July'!$E$7:$E$86,'July'!$D$7:$D$86,H11)+SUMIFS('August'!$E$7:$E$86,'August'!$D$7:$D$86,H11)+SUMIFS('September'!$E$7:$E$86,'September'!$D$7:$D$86,H11)+SUMIFS('October'!$E$7:$E$86,'October'!$D$7:$D$86,H11)+SUMIFS('November'!$E$7:$E$86,'November'!$D$7:$D$86,H11)+SUMIFS('December'!$E$7:$E$86,'December'!$D$7:$D$86,H11)) | J11: =IF(H11="","",'Setup'!F14)
B12: June | C12: =IF(COUNT('June'!$E$7:$E$86)>0,'June'!H6,"") | D12: =IF(COUNT('June'!$E$7:$E$86)>0,'June'!H7,"") | E12: =IF(COUNT('June'!$E$7:$E$86)>0,'June'!H8,"") | F12: =IF(COUNT('June'!$E$7:$E$86)>0,'June'!H9,"") | H12: =IF('Setup'!E15="","",'Setup'!E15) | I12: =IF(H12="","",SUMIFS('January'!$E$7:$E$86,'January'!$D$7:$D$86,H12)+SUMIFS('February'!$E$7:$E$86,'February'!$D$7:$D$86,H12)+SUMIFS('March'!$E$7:$E$86,'March'!$D$7:$D$86,H12)+SUMIFS('April'!$E$7:$E$86,'April'!$D$7:$D$86,H12)+SUMIFS('May'!$E$7:$E$86,'May'!$D$7:$D$86,H12)+SUMIFS('June'!$E$7:$E$86,'June'!$D$7:$D$86,H12)+SUMIFS('July'!$E$7:$E$86,'July'!$D$7:$D$86,H12)+SUMIFS('August'!$E$7:$E$86,'August'!$D$7:$D$86,H12)+SUMIFS('September'!$E$7:$E$86,'September'!$D$7:$D$86,H12)+SUMIFS('October'!$E$7:$E$86,'October'!$D$7:$D$86,H12)+SUMIFS('November'!$E$7:$E$86,'November'!$D$7:$D$86,H12)+SUMIFS('December'!$E$7:$E$86,'December'!$D$7:$D$86,H12)) | J12: =IF(H12="","",'Setup'!F15)
B13: July | C13: =IF(COUNT('July'!$E$7:$E$86)>0,'July'!H6,"") | D13: =IF(COUNT('July'!$E$7:$E$86)>0,'July'!H7,"") | E13: =IF(COUNT('July'!$E$7:$E$86)>0,'July'!H8,"") | F13: =IF(COUNT('July'!$E$7:$E$86)>0,'July'!H9,"") | H13: =IF('Setup'!E16="","",'Setup'!E16) | I13: =IF(H13="","",SUMIFS('January'!$E$7:$E$86,'January'!$D$7:$D$86,H13)+SUMIFS('February'!$E$7:$E$86,'February'!$D$7:$D$86,H13)+SUMIFS('March'!$E$7:$E$86,'March'!$D$7:$D$86,H13)+SUMIFS('April'!$E$7:$E$86,'April'!$D$7:$D$86,H13)+SUMIFS('May'!$E$7:$E$86,'May'!$D$7:$D$86,H13)+SUMIFS('June'!$E$7:$E$86,'June'!$D$7:$D$86,H13)+SUMIFS('July'!$E$7:$E$86,'July'!$D$7:$D$86,H13)+SUMIFS('August'!$E$7:$E$86,'August'!$D$7:$D$86,H13)+SUMIFS('September'!$E$7:$E$86,'September'!$D$7:$D$86,H13)+SUMIFS('October'!$E$7:$E$86,'October'!$D$7:$D$86,H13)+SUMIFS('November'!$E$7:$E$86,'November'!$D$7:$D$86,H13)+SUMIFS('December'!$E$7:$E$86,'December'!$D$7:$D$86,H13)) | J13: =IF(H13="","",'Setup'!F16)
B14: August | C14: =IF(COUNT('August'!$E$7:$E$86)>0,'August'!H6,"") | D14: =IF(COUNT('August'!$E$7:$E$86)>0,'August'!H7,"") | E14: =IF(COUNT('August'!$E$7:$E$86)>0,'August'!H8,"") | F14: =IF(COUNT('August'!$E$7:$E$86)>0,'August'!H9,"") | H14: =IF('Setup'!E17="","",'Setup'!E17) | I14: =IF(H14="","",SUMIFS('January'!$E$7:$E$86,'January'!$D$7:$D$86,H14)+SUMIFS('February'!$E$7:$E$86,'February'!$D$7:$D$86,H14)+SUMIFS('March'!$E$7:$E$86,'March'!$D$7:$D$86,H14)+SUMIFS('April'!$E$7:$E$86,'April'!$D$7:$D$86,H14)+SUMIFS('May'!$E$7:$E$86,'May'!$D$7:$D$86,H14)+SUMIFS('June'!$E$7:$E$86,'June'!$D$7:$D$86,H14)+SUMIFS('July'!$E$7:$E$86,'July'!$D$7:$D$86,H14)+SUMIFS('August'!$E$7:$E$86,'August'!$D$7:$D$86,H14)+SUMIFS('September'!$E$7:$E$86,'September'!$D$7:$D$86,H14)+SUMIFS('October'!$E$7:$E$86,'October'!$D$7:$D$86,H14)+SUMIFS('November'!$E$7:$E$86,'November'!$D$7:$D$86,H14)+SUMIFS('December'!$E$7:$E$86,'December'!$D$7:$D$86,H14)) | J14: =IF(H14="","",'Setup'!F17)
B15: September | C15: =IF(COUNT('September'!$E$7:$E$86)>0,'September'!H6,"") | D15: =IF(COUNT('September'!$E$7:$E$86)>0,'September'!H7,"") | E15: =IF(COUNT('September'!$E$7:$E$86)>0,'September'!H8,"") | F15: =IF(COUNT('September'!$E$7:$E$86)>0,'September'!H9,"") | H15: =IF('Setup'!E18="","",'Setup'!E18) | I15: =IF(H15="","",SUMIFS('January'!$E$7:$E$86,'January'!$D$7:$D$86,H15)+SUMIFS('February'!$E$7:$E$86,'February'!$D$7:$D$86,H15)+SUMIFS('March'!$E$7:$E$86,'March'!$D$7:$D$86,H15)+SUMIFS('April'!$E$7:$E$86,'April'!$D$7:$D$86,H15)+SUMIFS('May'!$E$7:$E$86,'May'!$D$7:$D$86,H15)+SUMIFS('June'!$E$7:$E$86,'June'!$D$7:$D$86,H15)+SUMIFS('July'!$E$7:$E$86,'July'!$D$7:$D$86,H15)+SUMIFS('August'!$E$7:$E$86,'August'!$D$7:$D$86,H15)+SUMIFS('September'!$E$7:$E$86,'September'!$D$7:$D$86,H15)+SUMIFS('October'!$E$7:$E$86,'October'!$D$7:$D$86,H15)+SUMIFS('November'!$E$7:$E$86,'November'!$D$7:$D$86,H15)+SUMIFS('December'!$E$7:$E$86,'December'!$D$7:$D$86,H15)) | J15: =IF(H15="","",'Setup'!F18)
B16: October | C16: =IF(COUNT('October'!$E$7:$E$86)>0,'October'!H6,"") | D16: =IF(COUNT('October'!$E$7:$E$86)>0,'October'!H7,"") | E16: =IF(COUNT('October'!$E$7:$E$86)>0,'October'!H8,"") | F16: =IF(COUNT('October'!$E$7:$E$86)>0,'October'!H9,"") | H16: =IF('Setup'!E19="","",'Setup'!E19) | I16: =IF(H16="","",SUMIFS('January'!$E$7:$E$86,'January'!$D$7:$D$86,H16)+SUMIFS('February'!$E$7:$E$86,'February'!$D$7:$D$86,H16)+SUMIFS('March'!$E$7:$E$86,'March'!$D$7:$D$86,H16)+SUMIFS('April'!$E$7:$E$86,'April'!$D$7:$D$86,H16)+SUMIFS('May'!$E$7:$E$86,'May'!$D$7:$D$86,H16)+SUMIFS('June'!$E$7:$E$86,'June'!$D$7:$D$86,H16)+SUMIFS('July'!$E$7:$E$86,'July'!$D$7:$D$86,H16)+SUMIFS('August'!$E$7:$E$86,'August'!$D$7:$D$86,H16)+SUMIFS('September'!$E$7:$E$86,'September'!$D$7:$D$86,H16)+SUMIFS('October'!$E$7:$E$86,'October'!$D$7:$D$86,H16)+SUMIFS('November'!$E$7:$E$86,'November'!$D$7:$D$86,H16)+SUMIFS('December'!$E$7:$E$86,'December'!$D$7:$D$86,H16)) | J16: =IF(H16="","",'Setup'!F19)
B17: November | C17: =IF(COUNT('November'!$E$7:$E$86)>0,'November'!H6,"") | D17: =IF(COUNT('November'!$E$7:$E$86)>0,'November'!H7,"") | E17: =IF(COUNT('November'!$E$7:$E$86)>0,'November'!H8,"") | F17: =IF(COUNT('November'!$E$7:$E$86)>0,'November'!H9,"") | H17: =IF('Setup'!E20="","",'Setup'!E20) | I17: =IF(H17="","",SUMIFS('January'!$E$7:$E$86,'January'!$D$7:$D$86,H17)+SUMIFS('February'!$E$7:$E$86,'February'!$D$7:$D$86,H17)+SUMIFS('March'!$E$7:$E$86,'March'!$D$7:$D$86,H17)+SUMIFS('April'!$E$7:$E$86,'April'!$D$7:$D$86,H17)+SUMIFS('May'!$E$7:$E$86,'May'!$D$7:$D$86,H17)+SUMIFS('June'!$E$7:$E$86,'June'!$D$7:$D$86,H17)+SUMIFS('July'!$E$7:$E$86,'July'!$D$7:$D$86,H17)+SUMIFS('August'!$E$7:$E$86,'August'!$D$7:$D$86,H17)+SUMIFS('September'!$E$7:$E$86,'September'!$D$7:$D$86,H17)+SUMIFS('October'!$E$7:$E$86,'October'!$D$7:$D$86,H17)+SUMIFS('November'!$E$7:$E$86,'November'!$D$7:$D$86,H17)+SUMIFS('December'!$E$7:$E$86,'December'!$D$7:$D$86,H17)) | J17: =IF(H17="","",'Setup'!F20)
B18: December | C18: =IF(COUNT('December'!$E$7:$E$86)>0,'December'!H6,"") | D18: =IF(COUNT('December'!$E$7:$E$86)>0,'December'!H7,"") | E18: =IF(COUNT('December'!$E$7:$E$86)>0,'December'!H8,"") | F18: =IF(COUNT('December'!$E$7:$E$86)>0,'December'!H9,"") | H18: =IF('Setup'!E21="","",'Setup'!E21) | I18: =IF(H18="","",SUMIFS('January'!$E$7:$E$86,'January'!$D$7:$D$86,H18)+SUMIFS('February'!$E$7:$E$86,'February'!$D$7:$D$86,H18)+SUMIFS('March'!$E$7:$E$86,'March'!$D$7:$D$86,H18)+SUMIFS('April'!$E$7:$E$86,'April'!$D$7:$D$86,H18)+SUMIFS('May'!$E$7:$E$86,'May'!$D$7:$D$86,H18)+SUMIFS('June'!$E$7:$E$86,'June'!$D$7:$D$86,H18)+SUMIFS('July'!$E$7:$E$86,'July'!$D$7:$D$86,H18)+SUMIFS('August'!$E$7:$E$86,'August'!$D$7:$D$86,H18)+SUMIFS('September'!$E$7:$E$86,'September'!$D$7:$D$86,H18)+SUMIFS('October'!$E$7:$E$86,'October'!$D$7:$D$86,H18)+SUMIFS('November'!$E$7:$E$86,'November'!$D$7:$D$86,H18)+SUMIFS('December'!$E$7:$E$86,'December'!$D$7:$D$86,H18)) | J18: =IF(H18="","",'Setup'!F21)
B19: Year | C19: =SUM(C7:C18) | D19: =SUM(D7:D18) | E19: =SUM(E7:E18) | F19: =SUM(F7:F18) | H19: =IF('Setup'!E22="","",'Setup'!E22) | I19: =IF(H19="","",SUMIFS('January'!$E$7:$E$86,'January'!$D$7:$D$86,H19)+SUMIFS('February'!$E$7:$E$86,'February'!$D$7:$D$86,H19)+SUMIFS('March'!$E$7:$E$86,'March'!$D$7:$D$86,H19)+SUMIFS('April'!$E$7:$E$86,'April'!$D$7:$D$86,H19)+SUMIFS('May'!$E$7:$E$86,'May'!$D$7:$D$86,H19)+SUMIFS('June'!$E$7:$E$86,'June'!$D$7:$D$86,H19)+SUMIFS('July'!$E$7:$E$86,'July'!$D$7:$D$86,H19)+SUMIFS('August'!$E$7:$E$86,'August'!$D$7:$D$86,H19)+SUMIFS('September'!$E$7:$E$86,'September'!$D$7:$D$86,H19)+SUMIFS('October'!$E$7:$E$86,'October'!$D$7:$D$86,H19)+SUMIFS('November'!$E$7:$E$86,'November'!$D$7:$D$86,H19)+SUMIFS('December'!$E$7:$E$86,'December'!$D$7:$D$86,H19)) | J19: =IF(H19="","",'Setup'!F22)
B20: Share to savings and debt | C20: =IF(C19=0,"",F19/C19) | H20: =IF('Setup'!E23="","",'Setup'!E23) | I20: =IF(H20="","",SUMIFS('January'!$E$7:$E$86,'January'!$D$7:$D$86,H20)+SUMIFS('February'!$E$7:$E$86,'February'!$D$7:$D$86,H20)+SUMIFS('March'!$E$7:$E$86,'March'!$D$7:$D$86,H20)+SUMIFS('April'!$E$7:$E$86,'April'!$D$7:$D$86,H20)+SUMIFS('May'!$E$7:$E$86,'May'!$D$7:$D$86,H20)+SUMIFS('June'!$E$7:$E$86,'June'!$D$7:$D$86,H20)+SUMIFS('July'!$E$7:$E$86,'July'!$D$7:$D$86,H20)+SUMIFS('August'!$E$7:$E$86,'August'!$D$7:$D$86,H20)+SUMIFS('September'!$E$7:$E$86,'September'!$D$7:$D$86,H20)+SUMIFS('October'!$E$7:$E$86,'October'!$D$7:$D$86,H20)+SUMIFS('November'!$E$7:$E$86,'November'!$D$7:$D$86,H20)+SUMIFS('December'!$E$7:$E$86,'December'!$D$7:$D$86,H20)) | J20: =IF(H20="","",'Setup'!F23)
H21: =IF('Setup'!E24="","",'Setup'!E24) | I21: =IF(H21="","",SUMIFS('January'!$E$7:$E$86,'January'!$D$7:$D$86,H21)+SUMIFS('February'!$E$7:$E$86,'February'!$D$7:$D$86,H21)+SUMIFS('March'!$E$7:$E$86,'March'!$D$7:$D$86,H21)+SUMIFS('April'!$E$7:$E$86,'April'!$D$7:$D$86,H21)+SUMIFS('May'!$E$7:$E$86,'May'!$D$7:$D$86,H21)+SUMIFS('June'!$E$7:$E$86,'June'!$D$7:$D$86,H21)+SUMIFS('July'!$E$7:$E$86,'July'!$D$7:$D$86,H21)+SUMIFS('August'!$E$7:$E$86,'August'!$D$7:$D$86,H21)+SUMIFS('September'!$E$7:$E$86,'September'!$D$7:$D$86,H21)+SUMIFS('October'!$E$7:$E$86,'October'!$D$7:$D$86,H21)+SUMIFS('November'!$E$7:$E$86,'November'!$D$7:$D$86,H21)+SUMIFS('December'!$E$7:$E$86,'December'!$D$7:$D$86,H21)) | J21: =IF(H21="","",'Setup'!F24)
H22: =IF('Setup'!E25="","",'Setup'!E25) | I22: =IF(H22="","",SUMIFS('January'!$E$7:$E$86,'January'!$D$7:$D$86,H22)+SUMIFS('February'!$E$7:$E$86,'February'!$D$7:$D$86,H22)+SUMIFS('March'!$E$7:$E$86,'March'!$D$7:$D$86,H22)+SUMIFS('April'!$E$7:$E$86,'April'!$D$7:$D$86,H22)+SUMIFS('May'!$E$7:$E$86,'May'!$D$7:$D$86,H22)+SUMIFS('June'!$E$7:$E$86,'June'!$D$7:$D$86,H22)+SUMIFS('July'!$E$7:$E$86,'July'!$D$7:$D$86,H22)+SUMIFS('August'!$E$7:$E$86,'August'!$D$7:$D$86,H22)+SUMIFS('September'!$E$7:$E$86,'September'!$D$7:$D$86,H22)+SUMIFS('October'!$E$7:$E$86,'October'!$D$7:$D$86,H22)+SUMIFS('November'!$E$7:$E$86,'November'!$D$7:$D$86,H22)+SUMIFS('December'!$E$7:$E$86,'December'!$D$7:$D$86,H22)) | J22: =IF(H22="","",'Setup'!F25)
B23: Group | C23: Spent this year | H23: =IF('Setup'!E26="","",'Setup'!E26) | I23: =IF(H23="","",SUMIFS('January'!$E$7:$E$86,'January'!$D$7:$D$86,H23)+SUMIFS('February'!$E$7:$E$86,'February'!$D$7:$D$86,H23)+SUMIFS('March'!$E$7:$E$86,'March'!$D$7:$D$86,H23)+SUMIFS('April'!$E$7:$E$86,'April'!$D$7:$D$86,H23)+SUMIFS('May'!$E$7:$E$86,'May'!$D$7:$D$86,H23)+SUMIFS('June'!$E$7:$E$86,'June'!$D$7:$D$86,H23)+SUMIFS('July'!$E$7:$E$86,'July'!$D$7:$D$86,H23)+SUMIFS('August'!$E$7:$E$86,'August'!$D$7:$D$86,H23)+SUMIFS('September'!$E$7:$E$86,'September'!$D$7:$D$86,H23)+SUMIFS('October'!$E$7:$E$86,'October'!$D$7:$D$86,H23)+SUMIFS('November'!$E$7:$E$86,'November'!$D$7:$D$86,H23)+SUMIFS('December'!$E$7:$E$86,'December'!$D$7:$D$86,H23)) | J23: =IF(H23="","",'Setup'!F26)
B24: Needs | C24: =SUMIF($J$7:$J$36,"Needs",$I$7:$I$36) | H24: =IF('Setup'!E27="","",'Setup'!E27) | I24: =IF(H24="","",SUMIFS('January'!$E$7:$E$86,'January'!$D$7:$D$86,H24)+SUMIFS('February'!$E$7:$E$86,'February'!$D$7:$D$86,H24)+SUMIFS('March'!$E$7:$E$86,'March'!$D$7:$D$86,H24)+SUMIFS('April'!$E$7:$E$86,'April'!$D$7:$D$86,H24)+SUMIFS('May'!$E$7:$E$86,'May'!$D$7:$D$86,H24)+SUMIFS('June'!$E$7:$E$86,'June'!$D$7:$D$86,H24)+SUMIFS('July'!$E$7:$E$86,'July'!$D$7:$D$86,H24)+SUMIFS('August'!$E$7:$E$86,'August'!$D$7:$D$86,H24)+SUMIFS('September'!$E$7:$E$86,'September'!$D$7:$D$86,H24)+SUMIFS('October'!$E$7:$E$86,'October'!$D$7:$D$86,H24)+SUMIFS('November'!$E$7:$E$86,'November'!$D$7:$D$86,H24)+SUMIFS('December'!$E$7:$E$86,'December'!$D$7:$D$86,H24)) | J24: =IF(H24="","",'Setup'!F27)
B25: Wants | C25: =SUMIF($J$7:$J$36,"Wants",$I$7:$I$36) | H25: =IF('Setup'!E28="","",'Setup'!E28) | I25: =IF(H25="","",SUMIFS('January'!$E$7:$E$86,'January'!$D$7:$D$86,H25)+SUMIFS('February'!$E$7:$E$86,'February'!$D$7:$D$86,H25)+SUMIFS('March'!$E$7:$E$86,'March'!$D$7:$D$86,H25)+SUMIFS('April'!$E$7:$E$86,'April'!$D$7:$D$86,H25)+SUMIFS('May'!$E$7:$E$86,'May'!$D$7:$D$86,H25)+SUMIFS('June'!$E$7:$E$86,'June'!$D$7:$D$86,H25)+SUMIFS('July'!$E$7:$E$86,'July'!$D$7:$D$86,H25)+SUMIFS('August'!$E$7:$E$86,'August'!$D$7:$D$86,H25)+SUMIFS('September'!$E$7:$E$86,'September'!$D$7:$D$86,H25)+SUMIFS('October'!$E$7:$E$86,'October'!$D$7:$D$86,H25)+SUMIFS('November'!$E$7:$E$86,'November'!$D$7:$D$86,H25)+SUMIFS('December'!$E$7:$E$86,'December'!$D$7:$D$86,H25)) | J25: =IF(H25="","",'Setup'!F28)
B26: Savings | C26: =SUMIF($J$7:$J$36,"Savings",$I$7:$I$36) | H26: =IF('Setup'!E29="","",'Setup'!E29) | I26: =IF(H26="","",SUMIFS('January'!$E$7:$E$86,'January'!$D$7:$D$86,H26)+SUMIFS('February'!$E$7:$E$86,'February'!$D$7:$D$86,H26)+SUMIFS('March'!$E$7:$E$86,'March'!$D$7:$D$86,H26)+SUMIFS('April'!$E$7:$E$86,'April'!$D$7:$D$86,H26)+SUMIFS('May'!$E$7:$E$86,'May'!$D$7:$D$86,H26)+SUMIFS('June'!$E$7:$E$86,'June'!$D$7:$D$86,H26)+SUMIFS('July'!$E$7:$E$86,'July'!$D$7:$D$86,H26)+SUMIFS('August'!$E$7:$E$86,'August'!$D$7:$D$86,H26)+SUMIFS('September'!$E$7:$E$86,'September'!$D$7:$D$86,H26)+SUMIFS('October'!$E$7:$E$86,'October'!$D$7:$D$86,H26)+SUMIFS('November'!$E$7:$E$86,'November'!$D$7:$D$86,H26)+SUMIFS('December'!$E$7:$E$86,'December'!$D$7:$D$86,H26)) | J26: =IF(H26="","",'Setup'!F29)
B27: Debt | C27: =SUMIF($J$7:$J$36,"Debt",$I$7:$I$36) | H27: =IF('Setup'!E30="","",'Setup'!E30) | I27: =IF(H27="","",SUMIFS('January'!$E$7:$E$86,'January'!$D$7:$D$86,H27)+SUMIFS('February'!$E$7:$E$86,'February'!$D$7:$D$86,H27)+SUMIFS('March'!$E$7:$E$86,'March'!$D$7:$D$86,H27)+SUMIFS('April'!$E$7:$E$86,'April'!$D$7:$D$86,H27)+SUMIFS('May'!$E$7:$E$86,'May'!$D$7:$D$86,H27)+SUMIFS('June'!$E$7:$E$86,'June'!$D$7:$D$86,H27)+SUMIFS('July'!$E$7:$E$86,'July'!$D$7:$D$86,H27)+SUMIFS('August'!$E$7:$E$86,'August'!$D$7:$D$86,H27)+SUMIFS('September'!$E$7:$E$86,'September'!$D$7:$D$86,H27)+SUMIFS('October'!$E$7:$E$86,'October'!$D$7:$D$86,H27)+SUMIFS('November'!$E$7:$E$86,'November'!$D$7:$D$86,H27)+SUMIFS('December'!$E$7:$E$86,'December'!$D$7:$D$86,H27)) | J27: =IF(H27="","",'Setup'!F30)
H28: =IF('Setup'!E31="","",'Setup'!E31) | I28: =IF(H28="","",SUMIFS('January'!$E$7:$E$86,'January'!$D$7:$D$86,H28)+SUMIFS('February'!$E$7:$E$86,'February'!$D$7:$D$86,H28)+SUMIFS('March'!$E$7:$E$86,'March'!$D$7:$D$86,H28)+SUMIFS('April'!$E$7:$E$86,'April'!$D$7:$D$86,H28)+SUMIFS('May'!$E$7:$E$86,'May'!$D$7:$D$86,H28)+SUMIFS('June'!$E$7:$E$86,'June'!$D$7:$D$86,H28)+SUMIFS('July'!$E$7:$E$86,'July'!$D$7:$D$86,H28)+SUMIFS('August'!$E$7:$E$86,'August'!$D$7:$D$86,H28)+SUMIFS('September'!$E$7:$E$86,'September'!$D$7:$D$86,H28)+SUMIFS('October'!$E$7:$E$86,'October'!$D$7:$D$86,H28)+SUMIFS('November'!$E$7:$E$86,'November'!$D$7:$D$86,H28)+SUMIFS('December'!$E$7:$E$86,'December'!$D$7:$D$86,H28)) | J28: =IF(H28="","",'Setup'!F31)
H29: =IF('Setup'!E32="","",'Setup'!E32) | I29: =IF(H29="","",SUMIFS('January'!$E$7:$E$86,'January'!$D$7:$D$86,H29)+SUMIFS('February'!$E$7:$E$86,'February'!$D$7:$D$86,H29)+SUMIFS('March'!$E$7:$E$86,'March'!$D$7:$D$86,H29)+SUMIFS('April'!$E$7:$E$86,'April'!$D$7:$D$86,H29)+SUMIFS('May'!$E$7:$E$86,'May'!$D$7:$D$86,H29)+SUMIFS('June'!$E$7:$E$86,'June'!$D$7:$D$86,H29)+SUMIFS('July'!$E$7:$E$86,'July'!$D$7:$D$86,H29)+SUMIFS('August'!$E$7:$E$86,'August'!$D$7:$D$86,H29)+SUMIFS('September'!$E$7:$E$86,'September'!$D$7:$D$86,H29)+SUMIFS('October'!$E$7:$E$86,'October'!$D$7:$D$86,H29)+SUMIFS('November'!$E$7:$E$86,'November'!$D$7:$D$86,H29)+SUMIFS('December'!$E$7:$E$86,'December'!$D$7:$D$86,H29)) | J29: =IF(H29="","",'Setup'!F32)
H30: =IF('Setup'!E33="","",'Setup'!E33) | I30: =IF(H30="","",SUMIFS('January'!$E$7:$E$86,'January'!$D$7:$D$86,H30)+SUMIFS('February'!$E$7:$E$86,'February'!$D$7:$D$86,H30)+SUMIFS('March'!$E$7:$E$86,'March'!$D$7:$D$86,H30)+SUMIFS('April'!$E$7:$E$86,'April'!$D$7:$D$86,H30)+SUMIFS('May'!$E$7:$E$86,'May'!$D$7:$D$86,H30)+SUMIFS('June'!$E$7:$E$86,'June'!$D$7:$D$86,H30)+SUMIFS('July'!$E$7:$E$86,'July'!$D$7:$D$86,H30)+SUMIFS('August'!$E$7:$E$86,'August'!$D$7:$D$86,H30)+SUMIFS('September'!$E$7:$E$86,'September'!$D$7:$D$86,H30)+SUMIFS('October'!$E$7:$E$86,'October'!$D$7:$D$86,H30)+SUMIFS('November'!$E$7:$E$86,'November'!$D$7:$D$86,H30)+SUMIFS('December'!$E$7:$E$86,'December'!$D$7:$D$86,H30)) | J30: =IF(H30="","",'Setup'!F33)
H31: =IF('Setup'!E34="","",'Setup'!E34) | I31: =IF(H31="","",SUMIFS('January'!$E$7:$E$86,'January'!$D$7:$D$86,H31)+SUMIFS('February'!$E$7:$E$86,'February'!$D$7:$D$86,H31)+SUMIFS('March'!$E$7:$E$86,'March'!$D$7:$D$86,H31)+SUMIFS('April'!$E$7:$E$86,'April'!$D$7:$D$86,H31)+SUMIFS('May'!$E$7:$E$86,'May'!$D$7:$D$86,H31)+SUMIFS('June'!$E$7:$E$86,'June'!$D$7:$D$86,H31)+SUMIFS('July'!$E$7:$E$86,'July'!$D$7:$D$86,H31)+SUMIFS('August'!$E$7:$E$86,'August'!$D$7:$D$86,H31)+SUMIFS('September'!$E$7:$E$86,'September'!$D$7:$D$86,H31)+SUMIFS('October'!$E$7:$E$86,'October'!$D$7:$D$86,H31)+SUMIFS('November'!$E$7:$E$86,'November'!$D$7:$D$86,H31)+SUMIFS('December'!$E$7:$E$86,'December'!$D$7:$D$86,H31)) | J31: =IF(H31="","",'Setup'!F34)
H32: =IF('Setup'!E35="","",'Setup'!E35) | I32: =IF(H32="","",SUMIFS('January'!$E$7:$E$86,'January'!$D$7:$D$86,H32)+SUMIFS('February'!$E$7:$E$86,'February'!$D$7:$D$86,H32)+SUMIFS('March'!$E$7:$E$86,'March'!$D$7:$D$86,H32)+SUMIFS('April'!$E$7:$E$86,'April'!$D$7:$D$86,H32)+SUMIFS('May'!$E$7:$E$86,'May'!$D$7:$D$86,H32)+SUMIFS('June'!$E$7:$E$86,'June'!$D$7:$D$86,H32)+SUMIFS('July'!$E$7:$E$86,'July'!$D$7:$D$86,H32)+SUMIFS('August'!$E$7:$E$86,'August'!$D$7:$D$86,H32)+SUMIFS('September'!$E$7:$E$86,'September'!$D$7:$D$86,H32)+SUMIFS('October'!$E$7:$E$86,'October'!$D$7:$D$86,H32)+SUMIFS('November'!$E$7:$E$86,'November'!$D$7:$D$86,H32)+SUMIFS('December'!$E$7:$E$86,'December'!$D$7:$D$86,H32)) | J32: =IF(H32="","",'Setup'!F35)
H33: =IF('Setup'!E36="","",'Setup'!E36) | I33: =IF(H33="","",SUMIFS('January'!$E$7:$E$86,'January'!$D$7:$D$86,H33)+SUMIFS('February'!$E$7:$E$86,'February'!$D$7:$D$86,H33)+SUMIFS('March'!$E$7:$E$86,'March'!$D$7:$D$86,H33)+SUMIFS('April'!$E$7:$E$86,'April'!$D$7:$D$86,H33)+SUMIFS('May'!$E$7:$E$86,'May'!$D$7:$D$86,H33)+SUMIFS('June'!$E$7:$E$86,'June'!$D$7:$D$86,H33)+SUMIFS('July'!$E$7:$E$86,'July'!$D$7:$D$86,H33)+SUMIFS('August'!$E$7:$E$86,'August'!$D$7:$D$86,H33)+SUMIFS('September'!$E$7:$E$86,'September'!$D$7:$D$86,H33)+SUMIFS('October'!$E$7:$E$86,'October'!$D$7:$D$86,H33)+SUMIFS('November'!$E$7:$E$86,'November'!$D$7:$D$86,H33)+SUMIFS('December'!$E$7:$E$86,'December'!$D$7:$D$86,H33)) | J33: =IF(H33="","",'Setup'!F36)
H34: =IF('Setup'!E37="","",'Setup'!E37) | I34: =IF(H34="","",SUMIFS('January'!$E$7:$E$86,'January'!$D$7:$D$86,H34)+SUMIFS('February'!$E$7:$E$86,'February'!$D$7:$D$86,H34)+SUMIFS('March'!$E$7:$E$86,'March'!$D$7:$D$86,H34)+SUMIFS('April'!$E$7:$E$86,'April'!$D$7:$D$86,H34)+SUMIFS('May'!$E$7:$E$86,'May'!$D$7:$D$86,H34)+SUMIFS('June'!$E$7:$E$86,'June'!$D$7:$D$86,H34)+SUMIFS('July'!$E$7:$E$86,'July'!$D$7:$D$86,H34)+SUMIFS('August'!$E$7:$E$86,'August'!$D$7:$D$86,H34)+SUMIFS('September'!$E$7:$E$86,'September'!$D$7:$D$86,H34)+SUMIFS('October'!$E$7:$E$86,'October'!$D$7:$D$86,H34)+SUMIFS('November'!$E$7:$E$86,'November'!$D$7:$D$86,H34)+SUMIFS('December'!$E$7:$E$86,'December'!$D$7:$D$86,H34)) | J34: =IF(H34="","",'Setup'!F37)
H35: =IF('Setup'!E38="","",'Setup'!E38) | I35: =IF(H35="","",SUMIFS('January'!$E$7:$E$86,'January'!$D$7:$D$86,H35)+SUMIFS('February'!$E$7:$E$86,'February'!$D$7:$D$86,H35)+SUMIFS('March'!$E$7:$E$86,'March'!$D$7:$D$86,H35)+SUMIFS('April'!$E$7:$E$86,'April'!$D$7:$D$86,H35)+SUMIFS('May'!$E$7:$E$86,'May'!$D$7:$D$86,H35)+SUMIFS('June'!$E$7:$E$86,'June'!$D$7:$D$86,H35)+SUMIFS('July'!$E$7:$E$86,'July'!$D$7:$D$86,H35)+SUMIFS('August'!$E$7:$E$86,'August'!$D$7:$D$86,H35)+SUMIFS('September'!$E$7:$E$86,'September'!$D$7:$D$86,H35)+SUMIFS('October'!$E$7:$E$86,'October'!$D$7:$D$86,H35)+SUMIFS('November'!$E$7:$E$86,'November'!$D$7:$D$86,H35)+SUMIFS('December'!$E$7:$E$86,'December'!$D$7:$D$86,H35)) | J35: =IF(H35="","",'Setup'!F38)
H36: =IF('Setup'!E39="","",'Setup'!E39) | I36: =IF(H36="","",SUMIFS('January'!$E$7:$E$86,'January'!$D$7:$D$86,H36)+SUMIFS('February'!$E$7:$E$86,'February'!$D$7:$D$86,H36)+SUMIFS('March'!$E$7:$E$86,'March'!$D$7:$D$86,H36)+SUMIFS('April'!$E$7:$E$86,'April'!$D$7:$D$86,H36)+SUMIFS('May'!$E$7:$E$86,'May'!$D$7:$D$86,H36)+SUMIFS('June'!$E$7:$E$86,'June'!$D$7:$D$86,H36)+SUMIFS('July'!$E$7:$E$86,'July'!$D$7:$D$86,H36)+SUMIFS('August'!$E$7:$E$86,'August'!$D$7:$D$86,H36)+SUMIFS('September'!$E$7:$E$86,'September'!$D$7:$D$86,H36)+SUMIFS('October'!$E$7:$E$86,'October'!$D$7:$D$86,H36)+SUMIFS('November'!$E$7:$E$86,'November'!$D$7:$D$86,H36)+SUMIFS('December'!$E$7:$E$86,'December'!$D$7:$D$86,H36)) | J36: =IF(H36="","",'Setup'!F39)

Sheet Setup
B2: Setup
B3: Fill this in once. Every other tab updates from here.
B4: Start here | C4: Dashboard | D4: Setup | E4: Months | F4: Bills | G4: Paycheck | H4: Debt | I4: Savings
B6: Year | C6: 2027
B7: Currency | C7: $
B9: Income source | C9: Monthly amount | E9: Category | F9: Group | G9: Monthly budget
B10: Paycheck | C10: 3600 | E10: Rent or mortgage | F10: Needs | G10: 1400
B11: Side income | C11: 300 | E11: Utilities | F11: Needs | G11: 180
E12: Groceries | F12: Needs | G12: 500
E13: Transport | F13: Needs | G13: 220
E14: Insurance | F14: Needs | G14: 160
E15: Phone and internet | F15: Needs | G15: 95
E16: Medical | F16: Needs | G16: 60
E17: Eating out | F17: Wants | G17: 150
B18: Expected income | C18: =SUM(C10:C17) | E18: Shopping | F18: Wants | G18: 120
E19: Subscriptions | F19: Wants | G19: 45
E20: Fun | F20: Wants | G20: 100
E21: Gifts | F21: Wants | G21: 40
E22: Personal care | F22: Wants | G22: 50
E23: Emergency fund | F23: Savings | G23: 200
E24: Sinking funds | F24: Savings | G24: 100
E25: Retirement | F25: Savings | G25: 150
E26: Credit card | F26: Debt | G26: 150
E27: Student loan | F27: Debt | G27: 180
E40: Total budget | G40: =SUM(G10:G39)
E41: Left to budget | G41: =C18-G40

Sheet January
B2: January
B3: Log what you spend. The summary on the right updates itself.
B4: Start here | D4: Dashboard | E4: Setup | F4: Months | G4: Bills | H4: Paycheck | I4: Debt | J4: Savings
B6: Date | C6: What | D6: Category | E6: Amount | G6: Income this month | H6: ='Setup'!$C$18 | I6: Type over this if your income was different
B7: 46390 | C7: Rent | D7: Rent or mortgage | E7: 1200 | G7: Spent | H7: =SUM(E7:E86)
B8: 46391 | C8: Weekly shop | D8: Groceries | E8: 112.4 | G8: Left over | H8: =H6-H7
B9: 46393 | C9: Bus pass | D9: Transport | E9: 60 | G9: Saved and debt paid | H9: =SUMPRODUCT(SUMIFS($E$7:$E$86,$D$7:$D$86,'Setup'!$E$10:$E$39)*(('Setup'!$F$10:$F$39="Savings")+('Setup'!$F$10:$F$39="Debt")))
B10: 46396 | C10: Pizza night | D10: Eating out | E10: 38.5
B11: 46398 | C11: Weekly shop | D11: Groceries | E11: 96.2 | G11: Category | H11: Budget | I11: Spent | J11: Left | K11: Used
B12: 46401 | C12: Phone bill | D12: Phone and internet | E12: 55 | G12: =IF('Setup'!E10="","",'Setup'!E10) | H12: =IF(G12="","",'Setup'!G10) | I12: =IF(G12="","",SUMIFS($E$7:$E$86,$D$7:$D$86,G12)) | J12: =IF(G12="","",H12-I12) | K12: =IF(OR(G12="",H12=0),"",I12/H12) | L12: =IF(K12="","",REPT("█",ROUND(MIN(1,MAX(0,K12))*10,0))&REPT("░",10-ROUND(MIN(1,MAX(0,K12))*10,0)))
B13: 46402 | C13: To emergency fund | D13: Emergency fund | E13: 200 | G13: =IF('Setup'!E11="","",'Setup'!E11) | H13: =IF(G13="","",'Setup'!G11) | I13: =IF(G13="","",SUMIFS($E$7:$E$86,$D$7:$D$86,G13)) | J13: =IF(G13="","",H13-I13) | K13: =IF(OR(G13="",H13=0),"",I13/H13) | L13: =IF(K13="","",REPT("█",ROUND(MIN(1,MAX(0,K13))*10,0))&REPT("░",10-ROUND(MIN(1,MAX(0,K13))*10,0)))
B14: 46405 | C14: Streaming | D14: Subscriptions | E14: 15.99 | G14: =IF('Setup'!E12="","",'Setup'!E12) | H14: =IF(G14="","",'Setup'!G12) | I14: =IF(G14="","",SUMIFS($E$7:$E$86,$D$7:$D$86,G14)) | J14: =IF(G14="","",H14-I14) | K14: =IF(OR(G14="",H14=0),"",I14/H14) | L14: =IF(K14="","",REPT("█",ROUND(MIN(1,MAX(0,K14))*10,0))&REPT("░",10-ROUND(MIN(1,MAX(0,K14))*10,0)))
B15: 46408 | C15: Card payment | D15: Credit card | E15: 150 | G15: =IF('Setup'!E13="","",'Setup'!E13) | H15: =IF(G15="","",'Setup'!G13) | I15: =IF(G15="","",SUMIFS($E$7:$E$86,$D$7:$D$86,G15)) | J15: =IF(G15="","",H15-I15) | K15: =IF(OR(G15="",H15=0),"",I15/H15) | L15: =IF(K15="","",REPT("█",ROUND(MIN(1,MAX(0,K15))*10,0))&REPT("░",10-ROUND(MIN(1,MAX(0,K15))*10,0)))
B16: 46411 | C16: Concert tickets | D16: Fun | E16: 120 | G16: =IF('Setup'!E14="","",'Setup'!E14) | H16: =IF(G16="","",'Setup'!G14) | I16: =IF(G16="","",SUMIFS($E$7:$E$86,$D$7:$D$86,G16)) | J16: =IF(G16="","",H16-I16) | K16: =IF(OR(G16="",H16=0),"",I16/H16) | L16: =IF(K16="","",REPT("█",ROUND(MIN(1,MAX(0,K16))*10,0))&REPT("░",10-ROUND(MIN(1,MAX(0,K16))*10,0)))
B17: 46412 | C17: Shoes | D17: Shopping | E17: 64 | G17: =IF('Setup'!E15="","",'Setup'!E15) | H17: =IF(G17="","",'Setup'!G15) | I17: =IF(G17="","",SUMIFS($E$7:$E$86,$D$7:$D$86,G17)) | J17: =IF(G17="","",H17-I17) | K17: =IF(OR(G17="",H17=0),"",I17/H17) | L17: =IF(K17="","",REPT("█",ROUND(MIN(1,MAX(0,K17))*10,0))&REPT("░",10-ROUND(MIN(1,MAX(0,K17))*10,0)))
G18: =IF('Setup'!E16="","",'Setup'!E16) | H18: =IF(G18="","",'Setup'!G16) | I18: =IF(G18="","",SUMIFS($E$7:$E$86,$D$7:$D$86,G18)) | J18: =IF(G18="","",H18-I18) | K18: =IF(OR(G18="",H18=0),"",I18/H18) | L18: =IF(K18="","",REPT("█",ROUND(MIN(1,MAX(0,K18))*10,0))&REPT("░",10-ROUND(MIN(1,MAX(0,K18))*10,0)))
G19: =IF('Setup'!E17="","",'Setup'!E17) | H19: =IF(G19="","",'Setup'!G17) | I19: =IF(G19="","",SUMIFS($E$7:$E$86,$D$7:$D$86,G19)) | J19: =IF(G19="","",H19-I19) | K19: =IF(OR(G19="",H19=0),"",I19/H19) | L19: =IF(K19="","",REPT("█",ROUND(MIN(1,MAX(0,K19))*10,0))&REPT("░",10-ROUND(MIN(1,MAX(0,K19))*10,0)))
G20: =IF('Setup'!E18="","",'Setup'!E18) | H20: =IF(G20="","",'Setup'!G18) | I20: =IF(G20="","",SUMIFS($E$7:$E$86,$D$7:$D$86,G20)) | J20: =IF(G20="","",H20-I20) | K20: =IF(OR(G20="",H20=0),"",I20/H20) | L20: =IF(K20="","",REPT("█",ROUND(MIN(1,MAX(0,K20))*10,0))&REPT("░",10-ROUND(MIN(1,MAX(0,K20))*10,0)))
G21: =IF('Setup'!E19="","",'Setup'!E19) | H21: =IF(G21="","",'Setup'!G19) | I21: =IF(G21="","",SUMIFS($E$7:$E$86,$D$7:$D$86,G21)) | J21: =IF(G21="","",H21-I21) | K21: =IF(OR(G21="",H21=0),"",I21/H21) | L21: =IF(K21="","",REPT("█",ROUND(MIN(1,MAX(0,K21))*10,0))&REPT("░",10-ROUND(MIN(1,MAX(0,K21))*10,0)))
G22: =IF('Setup'!E20="","",'Setup'!E20) | H22: =IF(G22="","",'Setup'!G20) | I22: =IF(G22="","",SUMIFS($E$7:$E$86,$D$7:$D$86,G22)) | J22: =IF(G22="","",H22-I22) | K22: =IF(OR(G22="",H22=0),"",I22/H22) | L22: =IF(K22="","",REPT("█",ROUND(MIN(1,MAX(0,K22))*10,0))&REPT("░",10-ROUND(MIN(1,MAX(0,K22))*10,0)))
G23: =IF('Setup'!E21="","",'Setup'!E21) | H23: =IF(G23="","",'Setup'!G21) | I23: =IF(G23="","",SUMIFS($E$7:$E$86,$D$7:$D$86,G23)) | J23: =IF(G23="","",H23-I23) | K23: =IF(OR(G23="",H23=0),"",I23/H23) | L23: =IF(K23="","",REPT("█",ROUND(MIN(1,MAX(0,K23))*10,0))&REPT("░",10-ROUND(MIN(1,MAX(0,K23))*10,0)))
G24: =IF('Setup'!E22="","",'Setup'!E22) | H24: =IF(G24="","",'Setup'!G22) | I24: =IF(G24="","",SUMIFS($E$7:$E$86,$D$7:$D$86,G24)) | J24: =IF(G24="","",H24-I24) | K24: =IF(OR(G24="",H24=0),"",I24/H24) | L24: =IF(K24="","",REPT("█",ROUND(MIN(1,MAX(0,K24))*10,0))&REPT("░",10-ROUND(MIN(1,MAX(0,K24))*10,0)))
G25: =IF('Setup'!E23="","",'Setup'!E23) | H25: =IF(G25="","",'Setup'!G23) | I25: =IF(G25="","",SUMIFS($E$7:$E$86,$D$7:$D$86,G25)) | J25: =IF(G25="","",H25-I25) | K25: =IF(OR(G25="",H25=0),"",I25/H25) | L25: =IF(K25="","",REPT("█",ROUND(MIN(1,MAX(0,K25))*10,0))&REPT("░",10-ROUND(MIN(1,MAX(0,K25))*10,0)))
G26: =IF('Setup'!E24="","",'Setup'!E24) | H26: =IF(G26="","",'Setup'!G24) | I26: =IF(G26="","",SUMIFS($E$7:$E$86,$D$7:$D$86,G26)) | J26: =IF(G26="","",H26-I26) | K26: =IF(OR(G26="",H26=0),"",I26/H26) | L26: =IF(K26="","",REPT("█",ROUND(MIN(1,MAX(0,K26))*10,0))&REPT("░",10-ROUND(MIN(1,MAX(0,K26))*10,0)))
G27: =IF('Setup'!E25="","",'Setup'!E25) | H27: =IF(G27="","",'Setup'!G25) | I27: =IF(G27="","",SUMIFS($E$7:$E$86,$D$7:$D$86,G27)) | J27: =IF(G27="","",H27-I27) | K27: =IF(OR(G27="",H27=0),"",I27/H27) | L27: =IF(K27="","",REPT("█",ROUND(MIN(1,MAX(0,K27))*10,0))&REPT("░",10-ROUND(MIN(1,MAX(0,K27))*10,0)))
G28: =IF('Setup'!E26="","",'Setup'!E26) | H28: =IF(G28="","",'Setup'!G26) | I28: =IF(G28="","",SUMIFS($E$7:$E$86,$D$7:$D$86,G28)) | J28: =IF(G28="","",H28-I28) | K28: =IF(OR(G28="",H28=0),"",I28/H28) | L28: =IF(K28="","",REPT("█",ROUND(MIN(1,MAX(0,K28))*10,0))&REPT("░",10-ROUND(MIN(1,MAX(0,K28))*10,0)))
G29: =IF('Setup'!E27="","",'Setup'!E27) | H29: =IF(G29="","",'Setup'!G27) | I29: =IF(G29="","",SUMIFS($E$7:$E$86,$D$7:$D$86,G29)) | J29: =IF(G29="","",H29-I29) | K29: =IF(OR(G29="",H29=0),"",I29/H29) | L29: =IF(K29="","",REPT("█",ROUND(MIN(1,MAX(0,K29))*10,0))&REPT("░",10-ROUND(MIN(1,MAX(0,K29))*10,0)))
... G41: =IF('Setup'!E39="","",'Setup'!E39) | H41: =IF(G41="","",'Setup'!G39) | I41: =IF(G41="","",SUMIFS($E$7:$E$86,$D$7:$D$86,G41)) | J41: =IF(G41="","",H41-I41) | K41: =IF(OR(G41="",H41=0),"",I41/H41) | L41: =IF(K41="","",REPT("█",ROUND(MIN(1,MAX(0,K41))*10,0))&REPT("░",10-ROUND(MIN(1,MAX(0,K41))*10,0)))

Sheet February
B2: February
B3: Log what you spend. The summary on the right updates itself.
B4: Start here | D4: Dashboard | E4: Setup | F4: Months | G4: Bills | H4: Paycheck | I4: Debt | J4: Savings
B6: Date | C6: What | D6: Category | E6: Amount | G6: Income this month | H6: ='Setup'!$C$18 | I6: Type over this if your income was different
G7: Spent | H7: =SUM(E7:E86)
G8: Left over | H8: =H6-H7
G9: Saved and debt paid | H9: =SUMPRODUCT(SUMIFS($E$7:$E$86,$D$7:$D$86,'Setup'!$E$10:$E$39)*(('Setup'!$F$10:$F$39="Savings")+('Setup'!$F$10:$F$39="Debt")))
G11: Category | H11: Budget | I11: Spent | J11: Left | K11: Used
G12: =IF('Setup'!E10="","",'Setup'!E10) | H12: =IF(G12="","",'Setup'!G10) | I12: =IF(G12="","",SUMIFS($E$7:$E$86,$D$7:$D$86,G12)) | J12: =IF(G12="","",H12-I12) | K12: =IF(OR(G12="",H12=0),"",I12/H12) | L12: =IF(K12="","",REPT("█",ROUND(MIN(1,MAX(0,K12))*10,0))&REPT("░",10-ROUND(MIN(1,MAX(0,K12))*10,0)))
G13: =IF('Setup'!E11="","",'Setup'!E11) | H13: =IF(G13="","",'Setup'!G11) | I13: =IF(G13="","",SUMIFS($E$7:$E$86,$D$7:$D$86,G13)) | J13: =IF(G13="","",H13-I13) | K13: =IF(OR(G13="",H13=0),"",I13/H13) | L13: =IF(K13="","",REPT("█",ROUND(MIN(1,MAX(0,K13))*10,0))&REPT("░",10-ROUND(MIN(1,MAX(0,K13))*10,0)))
G14: =IF('Setup'!E12="","",'Setup'!E12) | H14: =IF(G14="","",'Setup'!G12) | I14: =IF(G14="","",SUMIFS($E$7:$E$86,$D$7:$D$86,G14)) | J14: =IF(G14="","",H14-I14) | K14: =IF(OR(G14="",H14=0),"",I14/H14) | L14: =IF(K14="","",REPT("█",ROUND(MIN(1,MAX(0,K14))*10,0))&REPT("░",10-ROUND(MIN(1,MAX(0,K14))*10,0)))
G15: =IF('Setup'!E13="","",'Setup'!E13) | H15: =IF(G15="","",'Setup'!G13) | I15: =IF(G15="","",SUMIFS($E$7:$E$86,$D$7:$D$86,G15)) | J15: =IF(G15="","",H15-I15) | K15: =IF(OR(G15="",H15=0),"",I15/H15) | L15: =IF(K15="","",REPT("█",ROUND(MIN(1,MAX(0,K15))*10,0))&REPT("░",10-ROUND(MIN(1,MAX(0,K15))*10,0)))
G16: =IF('Setup'!E14="","",'Setup'!E14) | H16: =IF(G16="","",'Setup'!G14) | I16: =IF(G16="","",SUMIFS($E$7:$E$86,$D$7:$D$86,G16)) | J16: =IF(G16="","",H16-I16) | K16: =IF(OR(G16="",H16=0),"",I16/H16) | L16: =IF(K16="","",REPT("█",ROUND(MIN(1,MAX(0,K16))*10,0))&REPT("░",10-ROUND(MIN(1,MAX(0,K16))*10,0)))
G17: =IF('Setup'!E15="","",'Setup'!E15) | H17: =IF(G17="","",'Setup'!G15) | I17: =IF(G17="","",SUMIFS($E$7:$E$86,$D$7:$D$86,G17)) | J17: =IF(G17="","",H17-I17) | K17: =IF(OR(G17="",H17=0),"",I17/H17) | L17: =IF(K17="","",REPT("█",ROUND(MIN(1,MAX(0,K17))*10,0))&REPT("░",10-ROUND(MIN(1,MAX(0,K17))*10,0)))
G18: =IF('Setup'!E16="","",'Setup'!E16) | H18: =IF(G18="","",'Setup'!G16) | I18: =IF(G18="","",SUMIFS($E$7:$E$86,$D$7:$D$86,G18)) | J18: =IF(G18="","",H18-I18) | K18: =IF(OR(G18="",H18=0),"",I18/H18) | L18: =IF(K18="","",REPT("█",ROUND(MIN(1,MAX(0,K18))*10,0))&REPT("░",10-ROUND(MIN(1,MAX(0,K18))*10,0)))
G19: =IF('Setup'!E17="","",'Setup'!E17) | H19: =IF(G19="","",'Setup'!G17) | I19: =IF(G19="","",SUMIFS($E$7:$E$86,$D$7:$D$86,G19)) | J19: =IF(G19="","",H19-I19) | K19: =IF(OR(G19="",H19=0),"",I19/H19) | L19: =IF(K19="","",REPT("█",ROUND(MIN(1,MAX(0,K19))*10,0))&REPT("░",10-ROUND(MIN(1,MAX(0,K19))*10,0)))
G20: =IF('Setup'!E18="","",'Setup'!E18) | H20: =IF(G20="","",'Setup'!G18) | I20: =IF(G20="","",SUMIFS($E$7:$E$86,$D$7:$D$86,G20)) | J20: =IF(G20="","",H20-I20) | K20: =IF(OR(G20="",H20=0),"",I20/H20) | L20: =IF(K20="","",REPT("█",ROUND(MIN(1,MAX(0,K20))*10,0))&REPT("░",10-ROUND(MIN(1,MAX(0,K20))*10,0)))
G21: =IF('Setup'!E19="","",'Setup'!E19) | H21: =IF(G21="","",'Setup'!G19) | I21: =IF(G21="","",SUMIFS($E$7:$E$86,$D$7:$D$86,G21)) | J21: =IF(G21="","",H21-I21) | K21: =IF(OR(G21="",H21=0),"",I21/H21) | L21: =IF(K21="","",REPT("█",ROUND(MIN(1,MAX(0,K21))*10,0))&REPT("░",10-ROUND(MIN(1,MAX(0,K21))*10,0)))
G22: =IF('Setup'!E20="","",'Setup'!E20) | H22: =IF(G22="","",'Setup'!G20) | I22: =IF(G22="","",SUMIFS($E$7:$E$86,$D$7:$D$86,G22)) | J22: =IF(G22="","",H22-I22) | K22: =IF(OR(G22="",H22=0),"",I22/H22) | L22: =IF(K22="","",REPT("█",ROUND(MIN(1,MAX(0,K22))*10,0))&REPT("░",10-ROUND(MIN(1,MAX(0,K22))*10,0)))
G23: =IF('Setup'!E21="","",'Setup'!E21) | H23: =IF(G23="","",'Setup'!G21) | I23: =IF(G23="","",SUMIFS($E$7:$E$86,$D$7:$D$86,G23)) | J23: =IF(G23="","",H23-I23) | K23: =IF(OR(G23="",H23=0),"",I23/H23) | L23: =IF(K23="","",REPT("█",ROUND(MIN(1,MAX(0,K23))*10,0))&REPT("░",10-ROUND(MIN(1,MAX(0,K23))*10,0)))
... G41: =IF('Setup'!E39="","",'Setup'!E39) | H41: =IF(G41="","",'Setup'!G39) | I41: =IF(G41="","",SUMIFS($E$7:$E$86,$D$7:$D$86,G41)) | J41: =IF(G41="","",H41-I41) | K41: =IF(OR(G41="",H41=0),"",I41/H41) | L41: =IF(K41="","",REPT("█",ROUND(MIN(1,MAX(0,K41))*10,0))&REPT("░",10-ROUND(MIN(1,MAX(0,K41))*10,0)))

Sheet March
B2: March
B3: Log what you spend. The summary on the right updates itself.
B4: Start here | D4: Dashboard | E4: Setup | F4: Months | G4: Bills | H4: Paycheck | I4: Debt | J4: Savings
B6: Date | C6: What | D6: Category | E6: Amount | G6: Income this month | H6: ='Setup'!$C$18 | I6: Type over this if your income was different
G7: Spent | H7: =SUM(E7:E86)
G8: Left over | H8: =H6-H7
G9: Saved and debt paid | H9: =SUMPRODUCT(SUMIFS($E$7:$E$86,$D$7:$D$86,'Setup'!$E$10:$E$39)*(('Setup'!$F$10:$F$39="Savings")+('Setup'!$F$10:$F$39="Debt")))
G11: Category | H11: Budget | I11: Spent | J11: Left | K11: Used
G12: =IF('Setup'!E10="","",'Setup'!E10) | H12: =IF(G12="","",'Setup'!G10) | I12: =IF(G12="","",SUMIFS($E$7:$E$86,$D$7:$D$86,G12)) | J12: =IF(G12="","",H12-I12) | K12: =IF(OR(G12="",H12=0),"",I12/H12) | L12: =IF(K12="","",REPT("█",ROUND(MIN(1,MAX(0,K12))*10,0))&REPT("░",10-ROUND(MIN(1,MAX(0,K12))*10,0)))
G13: =IF('Setup'!E11="","",'Setup'!E11) | H13: =IF(G13="","",'Setup'!G11) | I13: =IF(G13="","",SUMIFS($E$7:$E$86,$D$7:$D$86,G13)) | J13: =IF(G13="","",H13-I13) | K13: =IF(OR(G13="",H13=0),"",I13/H13) | L13: =IF(K13="","",REPT("█",ROUND(MIN(1,MAX(0,K13))*10,0))&REPT("░",10-ROUND(MIN(1,MAX(0,K13))*10,0)))
G14: =IF('Setup'!E12="","",'Setup'!E12) | H14: =IF(G14="","",'Setup'!G12) | I14: =IF(G14="","",SUMIFS($E$7:$E$86,$D$7:$D$86,G14)) | J14: =IF(G14="","",H14-I14) | K14: =IF(OR(G14="",H14=0),"",I14/H14) | L14: =IF(K14="","",REPT("█",ROUND(MIN(1,MAX(0,K14))*10,0))&REPT("░",10-ROUND(MIN(1,MAX(0,K14))*10,0)))
G15: =IF('Setup'!E13="","",'Setup'!E13) | H15: =IF(G15="","",'Setup'!G13) | I15: =IF(G15="","",SUMIFS($E$7:$E$86,$D$7:$D$86,G15)) | J15: =IF(G15="","",H15-I15) | K15: =IF(OR(G15="",H15=0),"",I15/H15) | L15: =IF(K15="","",REPT("█",ROUND(MIN(1,MAX(0,K15))*10,0))&REPT("░",10-ROUND(MIN(1,MAX(0,K15))*10,0)))
G16: =IF('Setup'!E14="","",'Setup'!E14) | H16: =IF(G16="","",'Setup'!G14) | I16: =IF(G16="","",SUMIFS($E$7:$E$86,$D$7:$D$86,G16)) | J16: =IF(G16="","",H16-I16) | K16: =IF(OR(G16="",H16=0),"",I16/H16) | L16: =IF(K16="","",REPT("█",ROUND(MIN(1,MAX(0,K16))*10,0))&REPT("░",10-ROUND(MIN(1,MAX(0,K16))*10,0)))
G17: =IF('Setup'!E15="","",'Setup'!E15) | H17: =IF(G17="","",'Setup'!G15) | I17: =IF(G17="","",SUMIFS($E$7:$E$86,$D$7:$D$86,G17)) | J17: =IF(G17="","",H17-I17) | K17: =IF(OR(G17="",H17=0),"",I17/H17) | L17: =IF(K17="","",REPT("█",ROUND(MIN(1,MAX(0,K17))*10,0))&REPT("░",10-ROUND(MIN(1,MAX(0,K17))*10,0)))
G18: =IF('Setup'!E16="","",'Setup'!E16) | H18: =IF(G18="","",'Setup'!G16) | I18: =IF(G18="","",SUMIFS($E$7:$E$86,$D$7:$D$86,G18)) | J18: =IF(G18="","",H18-I18) | K18: =IF(OR(G18="",H18=0),"",I18/H18) | L18: =IF(K18="","",REPT("█",ROUND(MIN(1,MAX(0,K18))*10,0))&REPT("░",10-ROUND(MIN(1,MAX(0,K18))*10,0)))
G19: =IF('Setup'!E17="","",'Setup'!E17) | H19: =IF(G19="","",'Setup'!G17) | I19: =IF(G19="","",SUMIFS($E$7:$E$86,$D$7:$D$86,G19)) | J19: =IF(G19="","",H19-I19) | K19: =IF(OR(G19="",H19=0),"",I19/H19) | L19: =IF(K19="","",REPT("█",ROUND(MIN(1,MAX(0,K19))*10,0))&REPT("░",10-ROUND(MIN(1,MAX(0,K19))*10,0)))
G20: =IF('Setup'!E18="","",'Setup'!E18) | H20: =IF(G20="","",'Setup'!G18) | I20: =IF(G20="","",SUMIFS($E$7:$E$86,$D$7:$D$86,G20)) | J20: =IF(G20="","",H20-I20) | K20: =IF(OR(G20="",H20=0),"",I20/H20) | L20: =IF(K20="","",REPT("█",ROUND(MIN(1,MAX(0,K20))*10,0))&REPT("░",10-ROUND(MIN(1,MAX(0,K20))*10,0)))
G21: =IF('Setup'!E19="","",'Setup'!E19) | H21: =IF(G21="","",'Setup'!G19) | I21: =IF(G21="","",SUMIFS($E$7:$E$86,$D$7:$D$86,G21)) | J21: =IF(G21="","",H21-I21) | K21: =IF(OR(G21="",H21=0),"",I21/H21) | L21: =IF(K21="","",REPT("█",ROUND(MIN(1,MAX(0,K21))*10,0))&REPT("░",10-ROUND(MIN(1,MAX(0,K21))*10,0)))
G22: =IF('Setup'!E20="","",'Setup'!E20) | H22: =IF(G22="","",'Setup'!G20) | I22: =IF(G22="","",SUMIFS($E$7:$E$86,$D$7:$D$86,G22)) | J22: =IF(G22="","",H22-I22) | K22: =IF(OR(G22="",H22=0),"",I22/H22) | L22: =IF(K22="","",REPT("█",ROUND(MIN(1,MAX(0,K22))*10,0))&REPT("░",10-ROUND(MIN(1,MAX(0,K22))*10,0)))
G23: =IF('Setup'!E21="","",'Setup'!E21) | H23: =IF(G23="","",'Setup'!G21) | I23: =IF(G23="","",SUMIFS($E$7:$E$86,$D$7:$D$86,G23)) | J23: =IF(G23="","",H23-I23) | K23: =IF(OR(G23="",H23=0),"",I23/H23) | L23: =IF(K23="","",REPT("█",ROUND(MIN(1,MAX(0,K23))*10,0))&REPT("░",10-ROUND(MIN(1,MAX(0,K23))*10,0)))
... G41: =IF('Setup'!E39="","",'Setup'!E39) | H41: =IF(G41="","",'Setup'!G39) | I41: =IF(G41="","",SUMIFS($E$7:$E$86,$D$7:$D$86,G41)) | J41: =IF(G41="","",H41-I41) | K41: =IF(OR(G41="",H41=0),"",I41/H41) | L41: =IF(K41="","",REPT("█",ROUND(MIN(1,MAX(0,K41))*10,0))&REPT("░",10-ROUND(MIN(1,MAX(0,K41))*10,0)))

Sheet April
B2: April
B3: Log what you spend. The summary on the right updates itself.
B4: Start here | D4: Dashboard | E4: Setup | F4: Months | G4: Bills | H4: Paycheck | I4: Debt | J4: Savings
B6: Date | C6: What | D6: Category | E6: Amount | G6: Income this month | H6: ='Setup'!$C$18 | I6: Type over this if your income was different
G7: Spent | H7: =SUM(E7:E86)
G8: Left over | H8: =H6-H7
G9: Saved and debt paid | H9: =SUMPRODUCT(SUMIFS($E$7:$E$86,$D$7:$D$86,'Setup'!$E$10:$E$39)*(('Setup'!$F$10:$F$39="Savings")+('Setup'!$F$10:$F$39="Debt")))
G11: Category | H11: Budget | I11: Spent | J11: Left | K11: Used
G12: =IF('Setup'!E10="","",'Setup'!E10) | H12: =IF(G12="","",'Setup'!G10) | I12: =IF(G12="","",SUMIFS($E$7:$E$86,$D$7:$D$86,G12)) | J12: =IF(G12="","",H12-I12) | K12: =IF(OR(G12="",H12=0),"",I12/H12) | L12: =IF(K12="","",REPT("█",ROUND(MIN(1,MAX(0,K12))*10,0))&REPT("░",10-ROUND(MIN(1,MAX(0,K12))*10,0)))
G13: =IF('Setup'!E11="","",'Setup'!E11) | H13: =IF(G13="","",'Setup'!G11) | I13: =IF(G13="","",SUMIFS($E$7:$E$86,$D$7:$D$86,G13)) | J13: =IF(G13="","",H13-I13) | K13: =IF(OR(G13="",H13=0),"",I13/H13) | L13: =IF(K13="","",REPT("█",ROUND(MIN(1,MAX(0,K13))*10,0))&REPT("░",10-ROUND(MIN(1,MAX(0,K13))*10,0)))
G14: =IF('Setup'!E12="","",'Setup'!E12) | H14: =IF(G14="","",'Setup'!G12) | I14: =IF(G14="","",SUMIFS($E$7:$E$86,$D$7:$D$86,G14)) | J14: =IF(G14="","",H14-I14) | K14: =IF(OR(G14="",H14=0),"",I14/H14) | L14: =IF(K14="","",REPT("█",ROUND(MIN(1,MAX(0,K14))*10,0))&REPT("░",10-ROUND(MIN(1,MAX(0,K14))*10,0)))
G15: =IF('Setup'!E13="","",'Setup'!E13) | H15: =IF(G15="","",'Setup'!G13) | I15: =IF(G15="","",SUMIFS($E$7:$E$86,$D$7:$D$86,G15)) | J15: =IF(G15="","",H15-I15) | K15: =IF(OR(G15="",H15=0),"",I15/H15) | L15: =IF(K15="","",REPT("█",ROUND(MIN(1,MAX(0,K15))*10,0))&REPT("░",10-ROUND(MIN(1,MAX(0,K15))*10,0)))
G16: =IF('Setup'!E14="","",'Setup'!E14) | H16: =IF(G16="","",'Setup'!G14) | I16: =IF(G16="","",SUMIFS($E$7:$E$86,$D$7:$D$86,G16)) | J16: =IF(G16="","",H16-I16) | K16: =IF(OR(G16="",H16=0),"",I16/H16) | L16: =IF(K16="","",REPT("█",ROUND(MIN(1,MAX(0,K16))*10,0))&REPT("░",10-ROUND(MIN(1,MAX(0,K16))*10,0)))
G17: =IF('Setup'!E15="","",'Setup'!E15) | H17: =IF(G17="","",'Setup'!G15) | I17: =IF(G17="","",SUMIFS($E$7:$E$86,$D$7:$D$86,G17)) | J17: =IF(G17="","",H17-I17) | K17: =IF(OR(G17="",H17=0),"",I17/H17) | L17: =IF(K17="","",REPT("█",ROUND(MIN(1,MAX(0,K17))*10,0))&REPT("░",10-ROUND(MIN(1,MAX(0,K17))*10,0)))
G18: =IF('Setup'!E16="","",'Setup'!E16) | H18: =IF(G18="","",'Setup'!G16) | I18: =IF(G18="","",SUMIFS($E$7:$E$86,$D$7:$D$86,G18)) | J18: =IF(G18="","",H18-I18) | K18: =IF(OR(G18="",H18=0),"",I18/H18) | L18: =IF(K18="","",REPT("█",ROUND(MIN(1,MAX(0,K18))*10,0))&REPT("░",10-ROUND(MIN(1,MAX(0,K18))*10,0)))
G19: =IF('Setup'!E17="","",'Setup'!E17) | H19: =IF(G19="","",'Setup'!G17) | I19: =IF(G19="","",SUMIFS($E$7:$E$86,$D$7:$D$86,G19)) | J19: =IF(G19="","",H19-I19) | K19: =IF(OR(G19="",H19=0),"",I19/H19) | L19: =IF(K19="","",REPT("█",ROUND(MIN(1,MAX(0,K19))*10,0))&REPT("░",10-ROUND(MIN(1,MAX(0,K19))*10,0)))
G20: =IF('Setup'!E18="","",'Setup'!E18) | H20: =IF(G20="","",'Setup'!G18) | I20: =IF(G20="","",SUMIFS($E$7:$E$86,$D$7:$D$86,G20)) | J20: =IF(G20="","",H20-I20) | K20: =IF(OR(G20="",H20=0),"",I20/H20) | L20: =IF(K20="","",REPT("█",ROUND(MIN(1,MAX(0,K20))*10,0))&REPT("░",10-ROUND(MIN(1,MAX(0,K20))*10,0)))
G21: =IF('Setup'!E19="","",'Setup'!E19) | H21: =IF(G21="","",'Setup'!G19) | I21: =IF(G21="","",SUMIFS($E$7:$E$86,$D$7:$D$86,G21)) | J21: =IF(G21="","",H21-I21) | K21: =IF(OR(G21="",H21=0),"",I21/H21) | L21: =IF(K21="","",REPT("█",ROUND(MIN(1,MAX(0,K21))*10,0))&REPT("░",10-ROUND(MIN(1,MAX(0,K21))*10,0)))
G22: =IF('Setup'!E20="","",'Setup'!E20) | H22: =IF(G22="","",'Setup'!G20) | I22: =IF(G22="","",SUMIFS($E$7:$E$86,$D$7:$D$86,G22)) | J22: =IF(G22="","",H22-I22) | K22: =IF(OR(G22="",H22=0),"",I22/H22) | L22: =IF(K22="","",REPT("█",ROUND(MIN(1,MAX(0,K22))*10,0))&REPT("░",10-ROUND(MIN(1,MAX(0,K22))*10,0)))
G23: =IF('Setup'!E21="","",'Setup'!E21) | H23: =IF(G23="","",'Setup'!G21) | I23: =IF(G23="","",SUMIFS($E$7:$E$86,$D$7:$D$86,G23)) | J23: =IF(G23="","",H23-I23) | K23: =IF(OR(G23="",H23=0),"",I23/H23) | L23: =IF(K23="","",REPT("█",ROUND(MIN(1,MAX(0,K23))*10,0))&REPT("░",10-ROUND(MIN(1,MAX(0,K23))*10,0)))
... G41: =IF('Setup'!E39="","",'Setup'!E39) | H41: =IF(G41="","",'Setup'!G39) | I41: =IF(G41="","",SUMIFS($E$7:$E$86,$D$7:$D$86,G41)) | J41: =IF(G41="","",H41-I41) | K41: =IF(OR(G41="",H41=0),"",I41/H41) | L41: =IF(K41="","",REPT("█",ROUND(MIN(1,MAX(0,K41))*10,0))&REPT("░",10-ROUND(MIN(1,MAX(0,K41))*10,0)))

Sheet May
B2: May
B3: Log what you spend. The summary on the right updates itself.
B4: Start here | D4: Dashboard | E4: Setup | F4: Months | G4: Bills | H4: Paycheck | I4: Debt | J4: Savings
B6: Date | C6: What | D6: Category | E6: Amount | G6: Income this month | H6: ='Setup'!$C$18 | I6: Type over this if your income was different
G7: Spent | H7: =SUM(E7:E86)
G8: Left over | H8: =H6-H7
G9: Saved and debt paid | H9: =SUMPRODUCT(SUMIFS($E$7:$E$86,$D$7:$D$86,'Setup'!$E$10:$E$39)*(('Setup'!$F$10:$F$39="Savings")+('Setup'!$F$10:$F$39="Debt")))
G11: Category | H11: Budget | I11: Spent | J11: Left | K11: Used
G12: =IF('Setup'!E10="","",'Setup'!E10) | H12: =IF(G12="","",'Setup'!G10) | I12: =IF(G12="","",SUMIFS($E$7:$E$86,$D$7:$D$86,G12)) | J12: =IF(G12="","",H12-I12) | K12: =IF(OR(G12="",H12=0),"",I12/H12) | L12: =IF(K12="","",REPT("█",ROUND(MIN(1,MAX(0,K12))*10,0))&REPT("░",10-ROUND(MIN(1,MAX(0,K12))*10,0)))
G13: =IF('Setup'!E11="","",'Setup'!E11) | H13: =IF(G13="","",'Setup'!G11) | I13: =IF(G13="","",SUMIFS($E$7:$E$86,$D$7:$D$86,G13)) | J13: =IF(G13="","",H13-I13) | K13: =IF(OR(G13="",H13=0),"",I13/H13) | L13: =IF(K13="","",REPT("█",ROUND(MIN(1,MAX(0,K13))*10,0))&REPT("░",10-ROUND(MIN(1,MAX(0,K13))*10,0)))
G14: =IF('Setup'!E12="","",'Setup'!E12) | H14: =IF(G14="","",'Setup'!G12) | I14: =IF(G14="","",SUMIFS($E$7:$E$86,$D$7:$D$86,G14)) | J14: =IF(G14="","",H14-I14) | K14: =IF(OR(G14="",H14=0),"",I14/H14) | L14: =IF(K14="","",REPT("█",ROUND(MIN(1,MAX(0,K14))*10,0))&REPT("░",10-ROUND(MIN(1,MAX(0,K14))*10,0)))
G15: =IF('Setup'!E13="","",'Setup'!E13) | H15: =IF(G15="","",'Setup'!G13) | I15: =IF(G15="","",SUMIFS($E$7:$E$86,$D$7:$D$86,G15)) | J15: =IF(G15="","",H15-I15) | K15: =IF(OR(G15="",H15=0),"",I15/H15) | L15: =IF(K15="","",REPT("█",ROUND(MIN(1,MAX(0,K15))*10,0))&REPT("░",10-ROUND(MIN(1,MAX(0,K15))*10,0)))
G16: =IF('Setup'!E14="","",'Setup'!E14) | H16: =IF(G16="","",'Setup'!G14) | I16: =IF(G16="","",SUMIFS($E$7:$E$86,$D$7:$D$86,G16)) | J16: =IF(G16="","",H16-I16) | K16: =IF(OR(G16="",H16=0),"",I16/H16) | L16: =IF(K16="","",REPT("█",ROUND(MIN(1,MAX(0,K16))*10,0))&REPT("░",10-ROUND(MIN(1,MAX(0,K16))*10,0)))
G17: =IF('Setup'!E15="","",'Setup'!E15) | H17: =IF(G17="","",'Setup'!G15) | I17: =IF(G17="","",SUMIFS($E$7:$E$86,$D$7:$D$86,G17)) | J17: =IF(G17="","",H17-I17) | K17: =IF(OR(G17="",H17=0),"",I17/H17) | L17: =IF(K17="","",REPT("█",ROUND(MIN(1,MAX(0,K17))*10,0))&REPT("░",10-ROUND(MIN(1,MAX(0,K17))*10,0)))
G18: =IF('Setup'!E16="","",'Setup'!E16) | H18: =IF(G18="","",'Setup'!G16) | I18: =IF(G18="","",SUMIFS($E$7:$E$86,$D$7:$D$86,G18)) | J18: =IF(G18="","",H18-I18) | K18: =IF(OR(G18="",H18=0),"",I18/H18) | L18: =IF(K18="","",REPT("█",ROUND(MIN(1,MAX(0,K18))*10,0))&REPT("░",10-ROUND(MIN(1,MAX(0,K18))*10,0)))
G19: =IF('Setup'!E17="","",'Setup'!E17) | H19: =IF(G19="","",'Setup'!G17) | I19: =IF(G19="","",SUMIFS($E$7:$E$86,$D$7:$D$86,G19)) | J19: =IF(G19="","",H19-I19) | K19: =IF(OR(G19="",H19=0),"",I19/H19) | L19: =IF(K19="","",REPT("█",ROUND(MIN(1,MAX(0,K19))*10,0))&REPT("░",10-ROUND(MIN(1,MAX(0,K19))*10,0)))
G20: =IF('Setup'!E18="","",'Setup'!E18) | H20: =IF(G20="","",'Setup'!G18) | I20: =IF(G20="","",SUMIFS($E$7:$E$86,$D$7:$D$86,G20)) | J20: =IF(G20="","",H20-I20) | K20: =IF(OR(G20="",H20=0),"",I20/H20) | L20: =IF(K20="","",REPT("█",ROUND(MIN(1,MAX(0,K20))*10,0))&REPT("░",10-ROUND(MIN(1,MAX(0,K20))*10,0)))
G21: =IF('Setup'!E19="","",'Setup'!E19) | H21: =IF(G21="","",'Setup'!G19) | I21: =IF(G21="","",SUMIFS($E$7:$E$86,$D$7:$D$86,G21)) | J21: =IF(G21="","",H21-I21) | K21: =IF(OR(G21="",H21=0),"",I21/H21) | L21: =IF(K21="","",REPT("█",ROUND(MIN(1,MAX(0,K21))*10,0))&REPT("░",10-ROUND(MIN(1,MAX(0,K21))*10,0)))
G22: =IF('Setup'!E20="","",'Setup'!E20) | H22: =IF(G22="","",'Setup'!G20) | I22: =IF(G22="","",SUMIFS($E$7:$E$86,$D$7:$D$86,G22)) | J22: =IF(G22="","",H22-I22) | K22: =IF(OR(G22="",H22=0),"",I22/H22) | L22: =IF(K22="","",REPT("█",ROUND(MIN(1,MAX(0,K22))*10,0))&REPT("░",10-ROUND(MIN(1,MAX(0,K22))*10,0)))
G23: =IF('Setup'!E21="","",'Setup'!E21) | H23: =IF(G23="","",'Setup'!G21) | I23: =IF(G23="","",SUMIFS($E$7:$E$86,$D$7:$D$86,G23)) | J23: =IF(G23="","",H23-I23) | K23: =IF(OR(G23="",H23=0),"",I23/H23) | L23: =IF(K23="","",REPT("█",ROUND(MIN(1,MAX(0,K23))*10,0))&REPT("░",10-ROUND(MIN(1,MAX(0,K23))*10,0)))
... G41: =IF('Setup'!E39="","",'Setup'!E39) | H41: =IF(G41="","",'Setup'!G39) | I41: =IF(G41="","",SUMIFS($E$7:$E$86,$D$7:$D$86,G41)) | J41: =IF(G41="","",H41-I41) | K41: =IF(OR(G41="",H41=0),"",I41/H41) | L41: =IF(K41="","",REPT("█",ROUND(MIN(1,MAX(0,K41))*10,0))&REPT("░",10-ROUND(MIN(1,MAX(0,K41))*10,0)))

Sheet June
B2: June
B3: Log what you spend. The summary on the right updates itself.
B4: Start here | D4: Dashboard | E4: Setup | F4: Months | G4: Bills | H4: Paycheck | I4: Debt | J4: Savings
B6: Date | C6: What | D6: Category | E6: Amount | G6: Income this month | H6: ='Setup'!$C$18 | I6: Type over this if your income was different
G7: Spent | H7: =SUM(E7:E86)
G8: Left over | H8: =H6-H7
G9: Saved and debt paid | H9: =SUMPRODUCT(SUMIFS($E$7:$E$86,$D$7:$D$86,'Setup'!$E$10:$E$39)*(('Setup'!$F$10:$F$39="Savings")+('Setup'!$F$10:$F$39="Debt")))
G11: Category | H11: Budget | I11: Spent | J11: Left | K11: Used
G12: =IF('Setup'!E10="","",'Setup'!E10) | H12: =IF(G12="","",'Setup'!G10) | I12: =IF(G12="","",SUMIFS($E$7:$E$86,$D$7:$D$86,G12)) | J12: =IF(G12="","",H12-I12) | K12: =IF(OR(G12="",H12=0),"",I12/H12) | L12: =IF(K12="","",REPT("█",ROUND(MIN(1,MAX(0,K12))*10,0))&REPT("░",10-ROUND(MIN(1,MAX(0,K12))*10,0)))
G13: =IF('Setup'!E11="","",'Setup'!E11) | H13: =IF(G13="","",'Setup'!G11) | I13: =IF(G13="","",SUMIFS($E$7:$E$86,$D$7:$D$86,G13)) | J13: =IF(G13="","",H13-I13) | K13: =IF(OR(G13="",H13=0),"",I13/H13) | L13: =IF(K13="","",REPT("█",ROUND(MIN(1,MAX(0,K13))*10,0))&REPT("░",10-ROUND(MIN(1,MAX(0,K13))*10,0)))
G14: =IF('Setup'!E12="","",'Setup'!E12) | H14: =IF(G14="","",'Setup'!G12) | I14: =IF(G14="","",SUMIFS($E$7:$E$86,$D$7:$D$86,G14)) | J14: =IF(G14="","",H14-I14) | K14: =IF(OR(G14="",H14=0),"",I14/H14) | L14: =IF(K14="","",REPT("█",ROUND(MIN(1,MAX(0,K14))*10,0))&REPT("░",10-ROUND(MIN(1,MAX(0,K14))*10,0)))
G15: =IF('Setup'!E13="","",'Setup'!E13) | H15: =IF(G15="","",'Setup'!G13) | I15: =IF(G15="","",SUMIFS($E$7:$E$86,$D$7:$D$86,G15)) | J15: =IF(G15="","",H15-I15) | K15: =IF(OR(G15="",H15=0),"",I15/H15) | L15: =IF(K15="","",REPT("█",ROUND(MIN(1,MAX(0,K15))*10,0))&REPT("░",10-ROUND(MIN(1,MAX(0,K15))*10,0)))
G16: =IF('Setup'!E14="","",'Setup'!E14) | H16: =IF(G16="","",'Setup'!G14) | I16: =IF(G16="","",SUMIFS($E$7:$E$86,$D$7:$D$86,G16)) | J16: =IF(G16="","",H16-I16) | K16: =IF(OR(G16="",H16=0),"",I16/H16) | L16: =IF(K16="","",REPT("█",ROUND(MIN(1,MAX(0,K16))*10,0))&REPT("░",10-ROUND(MIN(1,MAX(0,K16))*10,0)))
G17: =IF('Setup'!E15="","",'Setup'!E15) | H17: =IF(G17="","",'Setup'!G15) | I17: =IF(G17="","",SUMIFS($E$7:$E$86,$D$7:$D$86,G17)) | J17: =IF(G17="","",H17-I17) | K17: =IF(OR(G17="",H17=0),"",I17/H17) | L17: =IF(K17="","",REPT("█",ROUND(MIN(1,MAX(0,K17))*10,0))&REPT("░",10-ROUND(MIN(1,MAX(0,K17))*10,0)))
G18: =IF('Setup'!E16="","",'Setup'!E16) | H18: =IF(G18="","",'Setup'!G16) | I18: =IF(G18="","",SUMIFS($E$7:$E$86,$D$7:$D$86,G18)) | J18: =IF(G18="","",H18-I18) | K18: =IF(OR(G18="",H18=0),"",I18/H18) | L18: =IF(K18="","",REPT("█",ROUND(MIN(1,MAX(0,K18))*10,0))&REPT("░",10-ROUND(MIN(1,MAX(0,K18))*10,0)))
G19: =IF('Setup'!E17="","",'Setup'!E17) | H19: =IF(G19="","",'Setup'!G17) | I19: =IF(G19="","",SUMIFS($E$7:$E$86,$D$7:$D$86,G19)) | J19: =IF(G19="","",H19-I19) | K19: =IF(OR(G19="",H19=0),"",I19/H19) | L19: =IF(K19="","",REPT("█",ROUND(MIN(1,MAX(0,K19))*10,0))&REPT("░",10-ROUND(MIN(1,MAX(0,K19))*10,0)))
G20: =IF('Setup'!E18="","",'Setup'!E18) | H20: =IF(G20="","",'Setup'!G18) | I20: =IF(G20="","",SUMIFS($E$7:$E$86,$D$7:$D$86,G20)) | J20: =IF(G20="","",H20-I20) | K20: =IF(OR(G20="",H20=0),"",I20/H20) | L20: =IF(K20="","",REPT("█",ROUND(MIN(1,MAX(0,K20))*10,0))&REPT("░",10-ROUND(MIN(1,MAX(0,K20))*10,0)))
G21: =IF('Setup'!E19="","",'Setup'!E19) | H21: =IF(G21="","",'Setup'!G19) | I21: =IF(G21="","",SUMIFS($E$7:$E$86,$D$7:$D$86,G21)) | J21: =IF(G21="","",H21-I21) | K21: =IF(OR(G21="",H21=0),"",I21/H21) | L21: =IF(K21="","",REPT("█",ROUND(MIN(1,MAX(0,K21))*10,0))&REPT("░",10-ROUND(MIN(1,MAX(0,K21))*10,0)))
G22: =IF('Setup'!E20="","",'Setup'!E20) | H22: =IF(G22="","",'Setup'!G20) | I22: =IF(G22="","",SUMIFS($E$7:$E$86,$D$7:$D$86,G22)) | J22: =IF(G22="","",H22-I22) | K22: =IF(OR(G22="",H22=0),"",I22/H22) | L22: =IF(K22="","",REPT("█",ROUND(MIN(1,MAX(0,K22))*10,0))&REPT("░",10-ROUND(MIN(1,MAX(0,K22))*10,0)))
G23: =IF('Setup'!E21="","",'Setup'!E21) | H23: =IF(G23="","",'Setup'!G21) | I23: =IF(G23="","",SUMIFS($E$7:$E$86,$D$7:$D$86,G23)) | J23: =IF(G23="","",H23-I23) | K23: =IF(OR(G23="",H23=0),"",I23/H23) | L23: =IF(K23="","",REPT("█",ROUND(MIN(1,MAX(0,K23))*10,0))&REPT("░",10-ROUND(MIN(1,MAX(0,K23))*10,0)))
... G41: =IF('Setup'!E39="","",'Setup'!E39) | H41: =IF(G41="","",'Setup'!G39) | I41: =IF(G41="","",SUMIFS($E$7:$E$86,$D$7:$D$86,G41)) | J41: =IF(G41="","",H41-I41) | K41: =IF(OR(G41="",H41=0),"",I41/H41) | L41: =IF(K41="","",REPT("█",ROUND(MIN(1,MAX(0,K41))*10,0))&REPT("░",10-ROUND(MIN(1,MAX(0,K41))*10,0)))

Sheet July
B2: July
B3: Log what you spend. The summary on the right updates itself.
B4: Start here | D4: Dashboard | E4: Setup | F4: Months | G4: Bills | H4: Paycheck | I4: Debt | J4: Savings
B6: Date | C6: What | D6: Category | E6: Amount | G6: Income this month | H6: ='Setup'!$C$18 | I6: Type over this if your income was different
G7: Spent | H7: =SUM(E7:E86)
G8: Left over | H8: =H6-H7
G9: Saved and debt paid | H9: =SUMPRODUCT(SUMIFS($E$7:$E$86,$D$7:$D$86,'Setup'!$E$10:$E$39)*(('Setup'!$F$10:$F$39="Savings")+('Setup'!$F$10:$F$39="Debt")))
G11: Category | H11: Budget | I11: Spent | J11: Left | K11: Used
G12: =IF('Setup'!E10="","",'Setup'!E10) | H12: =IF(G12="","",'Setup'!G10) | I12: =IF(G12="","",SUMIFS($E$7:$E$86,$D$7:$D$86,G12)) | J12: =IF(G12="","",H12-I12) | K12: =IF(OR(G12="",H12=0),"",I12/H12) | L12: =IF(K12="","",REPT("█",ROUND(MIN(1,MAX(0,K12))*10,0))&REPT("░",10-ROUND(MIN(1,MAX(0,K12))*10,0)))
G13: =IF('Setup'!E11="","",'Setup'!E11) | H13: =IF(G13="","",'Setup'!G11) | I13: =IF(G13="","",SUMIFS($E$7:$E$86,$D$7:$D$86,G13)) | J13: =IF(G13="","",H13-I13) | K13: =IF(OR(G13="",H13=0),"",I13/H13) | L13: =IF(K13="","",REPT("█",ROUND(MIN(1,MAX(0,K13))*10,0))&REPT("░",10-ROUND(MIN(1,MAX(0,K13))*10,0)))
G14: =IF('Setup'!E12="","",'Setup'!E12) | H14: =IF(G14="","",'Setup'!G12) | I14: =IF(G14="","",SUMIFS($E$7:$E$86,$D$7:$D$86,G14)) | J14: =IF(G14="","",H14-I14) | K14: =IF(OR(G14="",H14=0),"",I14/H14) | L14: =IF(K14="","",REPT("█",ROUND(MIN(1,MAX(0,K14))*10,0))&REPT("░",10-ROUND(MIN(1,MAX(0,K14))*10,0)))
G15: =IF('Setup'!E13="","",'Setup'!E13) | H15: =IF(G15="","",'Setup'!G13) | I15: =IF(G15="","",SUMIFS($E$7:$E$86,$D$7:$D$86,G15)) | J15: =IF(G15="","",H15-I15) | K15: =IF(OR(G15="",H15=0),"",I15/H15) | L15: =IF(K15="","",REPT("█",ROUND(MIN(1,MAX(0,K15))*10,0))&REPT("░",10-ROUND(MIN(1,MAX(0,K15))*10,0)))
G16: =IF('Setup'!E14="","",'Setup'!E14) | H16: =IF(G16="","",'Setup'!G14) | I16: =IF(G16="","",SUMIFS($E$7:$E$86,$D$7:$D$86,G16)) | J16: =IF(G16="","",H16-I16) | K16: =IF(OR(G16="",H16=0),"",I16/H16) | L16: =IF(K16="","",REPT("█",ROUND(MIN(1,MAX(0,K16))*10,0))&REPT("░",10-ROUND(MIN(1,MAX(0,K16))*10,0)))
G17: =IF('Setup'!E15="","",'Setup'!E15) | H17: =IF(G17="","",'Setup'!G15) | I17: =IF(G17="","",SUMIFS($E$7:$E$86,$D$7:$D$86,G17)) | J17: =IF(G17="","",H17-I17) | K17: =IF(OR(G17="",H17=0),"",I17/H17) | L17: =IF(K17="","",REPT("█",ROUND(MIN(1,MAX(0,K17))*10,0))&REPT("░",10-ROUND(MIN(1,MAX(0,K17))*10,0)))
G18: =IF('Setup'!E16="","",'Setup'!E16) | H18: =IF(G18="","",'Setup'!G16) | I18: =IF(G18="","",SUMIFS($E$7:$E$86,$D$7:$D$86,G18)) | J18: =IF(G18="","",H18-I18) | K18: =IF(OR(G18="",H18=0),"",I18/H18) | L18: =IF(K18="","",REPT("█",ROUND(MIN(1,MAX(0,K18))*10,0))&REPT("░",10-ROUND(MIN(1,MAX(0,K18))*10,0)))
G19: =IF('Setup'!E17="","",'Setup'!E17) | H19: =IF(G19="","",'Setup'!G17) | I19: =IF(G19="","",SUMIFS($E$7:$E$86,$D$7:$D$86,G19)) | J19: =IF(G19="","",H19-I19) | K19: =IF(OR(G19="",H19=0),"",I19/H19) | L19: =IF(K19="","",REPT("█",ROUND(MIN(1,MAX(0,K19))*10,0))&REPT("░",10-ROUND(MIN(1,MAX(0,K19))*10,0)))
G20: =IF('Setup'!E18="","",'Setup'!E18) | H20: =IF(G20="","",'Setup'!G18) | I20: =IF(G20="","",SUMIFS($E$7:$E$86,$D$7:$D$86,G20)) | J20: =IF(G20="","",H20-I20) | K20: =IF(OR(G20="",H20=0),"",I20/H20) | L20: =IF(K20="","",REPT("█",ROUND(MIN(1,MAX(0,K20))*10,0))&REPT("░",10-ROUND(MIN(1,MAX(0,K20))*10,0)))
G21: =IF('Setup'!E19="","",'Setup'!E19) | H21: =IF(G21="","",'Setup'!G19) | I21: =IF(G21="","",SUMIFS($E$7:$E$86,$D$7:$D$86,G21)) | J21: =IF(G21="","",H21-I21) | K21: =IF(OR(G21="",H21=0),"",I21/H21) | L21: =IF(K21="","",REPT("█",ROUND(MIN(1,MAX(0,K21))*10,0))&REPT("░",10-ROUND(MIN(1,MAX(0,K21))*10,0)))
G22: =IF('Setup'!E20="","",'Setup'!E20) | H22: =IF(G22="","",'Setup'!G20) | I22: =IF(G22="","",SUMIFS($E$7:$E$86,$D$7:$D$86,G22)) | J22: =IF(G22="","",H22-I22) | K22: =IF(OR(G22="",H22=0),"",I22/H22) | L22: =IF(K22="","",REPT("█",ROUND(MIN(1,MAX(0,K22))*10,0))&REPT("░",10-ROUND(MIN(1,MAX(0,K22))*10,0)))
G23: =IF('Setup'!E21="","",'Setup'!E21) | H23: =IF(G23="","",'Setup'!G21) | I23: =IF(G23="","",SUMIFS($E$7:$E$86,$D$7:$D$86,G23)) | J23: =IF(G23="","",H23-I23) | K23: =IF(OR(G23="",H23=0),"",I23/H23) | L23: =IF(K23="","",REPT("█",ROUND(MIN(1,MAX(0,K23))*10,0))&REPT("░",10-ROUND(MIN(1,MAX(0,K23))*10,0)))
... G41: =IF('Setup'!E39="","",'Setup'!E39) | H41: =IF(G41="","",'Setup'!G39) | I41: =IF(G41="","",SUMIFS($E$7:$E$86,$D$7:$D$86,G41)) | J41: =IF(G41="","",H41-I41) | K41: =IF(OR(G41="",H41=0),"",I41/H41) | L41: =IF(K41="","",REPT("█",ROUND(MIN(1,MAX(0,K41))*10,0))&REPT("░",10-ROUND(MIN(1,MAX(0,K41))*10,0)))

Sheet August
B2: August
B3: Log what you spend. The summary on the right updates itself.
B4: Start here | D4: Dashboard | E4: Setup | F4: Months | G4: Bills | H4: Paycheck | I4: Debt | J4: Savings
B6: Date | C6: What | D6: Category | E6: Amount | G6: Income this month | H6: ='Setup'!$C$18 | I6: Type over this if your income was different
G7: Spent | H7: =SUM(E7:E86)
G8: Left over | H8: =H6-H7
G9: Saved and debt paid | H9: =SUMPRODUCT(SUMIFS($E$7:$E$86,$D$7:$D$86,'Setup'!$E$10:$E$39)*(('Setup'!$F$10:$F$39="Savings")+('Setup'!$F$10:$F$39="Debt")))
G11: Category | H11: Budget | I11: Spent | J11: Left | K11: Used
G12: =IF('Setup'!E10="","",'Setup'!E10) | H12: =IF(G12="","",'Setup'!G10) | I12: =IF(G12="","",SUMIFS($E$7:$E$86,$D$7:$D$86,G12)) | J12: =IF(G12="","",H12-I12) | K12: =IF(OR(G12="",H12=0),"",I12/H12) | L12: =IF(K12="","",REPT("█",ROUND(MIN(1,MAX(0,K12))*10,0))&REPT("░",10-ROUND(MIN(1,MAX(0,K12))*10,0)))
G13: =IF('Setup'!E11="","",'Setup'!E11) | H13: =IF(G13="","",'Setup'!G11) | I13: =IF(G13="","",SUMIFS($E$7:$E$86,$D$7:$D$86,G13)) | J13: =IF(G13="","",H13-I13) | K13: =IF(OR(G13="",H13=0),"",I13/H13) | L13: =IF(K13="","",REPT("█",ROUND(MIN(1,MAX(0,K13))*10,0))&REPT("░",10-ROUND(MIN(1,MAX(0,K13))*10,0)))
G14: =IF('Setup'!E12="","",'Setup'!E12) | H14: =IF(G14="","",'Setup'!G12) | I14: =IF(G14="","",SUMIFS($E$7:$E$86,$D$7:$D$86,G14)) | J14: =IF(G14="","",H14-I14) | K14: =IF(OR(G14="",H14=0),"",I14/H14) | L14: =IF(K14="","",REPT("█",ROUND(MIN(1,MAX(0,K14))*10,0))&REPT("░",10-ROUND(MIN(1,MAX(0,K14))*10,0)))
G15: =IF('Setup'!E13="","",'Setup'!E13) | H15: =IF(G15="","",'Setup'!G13) | I15: =IF(G15="","",SUMIFS($E$7:$E$86,$D$7:$D$86,G15)) | J15: =IF(G15="","",H15-I15) | K15: =IF(OR(G15="",H15=0),"",I15/H15) | L15: =IF(K15="","",REPT("█",ROUND(MIN(1,MAX(0,K15))*10,0))&REPT("░",10-ROUND(MIN(1,MAX(0,K15))*10,0)))
G16: =IF('Setup'!E14="","",'Setup'!E14) | H16: =IF(G16="","",'Setup'!G14) | I16: =IF(G16="","",SUMIFS($E$7:$E$86,$D$7:$D$86,G16)) | J16: =IF(G16="","",H16-I16) | K16: =IF(OR(G16="",H16=0),"",I16/H16) | L16: =IF(K16="","",REPT("█",ROUND(MIN(1,MAX(0,K16))*10,0))&REPT("░",10-ROUND(MIN(1,MAX(0,K16))*10,0)))
G17: =IF('Setup'!E15="","",'Setup'!E15) | H17: =IF(G17="","",'Setup'!G15) | I17: =IF(G17="","",SUMIFS($E$7:$E$86,$D$7:$D$86,G17)) | J17: =IF(G17="","",H17-I17) | K17: =IF(OR(G17="",H17=0),"",I17/H17) | L17: =IF(K17="","",REPT("█",ROUND(MIN(1,MAX(0,K17))*10,0))&REPT("░",10-ROUND(MIN(1,MAX(0,K17))*10,0)))
G18: =IF('Setup'!E16="","",'Setup'!E16) | H18: =IF(G18="","",'Setup'!G16) | I18: =IF(G18="","",SUMIFS($E$7:$E$86,$D$7:$D$86,G18)) | J18: =IF(G18="","",H18-I18) | K18: =IF(OR(G18="",H18=0),"",I18/H18) | L18: =IF(K18="","",REPT("█",ROUND(MIN(1,MAX(0,K18))*10,0))&REPT("░",10-ROUND(MIN(1,MAX(0,K18))*10,0)))
G19: =IF('Setup'!E17="","",'Setup'!E17) | H19: =IF(G19="","",'Setup'!G17) | I19: =IF(G19="","",SUMIFS($E$7:$E$86,$D$7:$D$86,G19)) | J19: =IF(G19="","",H19-I19) | K19: =IF(OR(G19="",H19=0),"",I19/H19) | L19: =IF(K19="","",REPT("█",ROUND(MIN(1,MAX(0,K19))*10,0))&REPT("░",10-ROUND(MIN(1,MAX(0,K19))*10,0)))
G20: =IF('Setup'!E18="","",'Setup'!E18) | H20: =IF(G20="","",'Setup'!G18) | I20: =IF(G20="","",SUMIFS($E$7:$E$86,$D$7:$D$86,G20)) | J20: =IF(G20="","",H20-I20) | K20: =IF(OR(G20="",H20=0),"",I20/H20) | L20: =IF(K20="","",REPT("█",ROUND(MIN(1,MAX(0,K20))*10,0))&REPT("░",10-ROUND(MIN(1,MAX(0,K20))*10,0)))
G21: =IF('Setup'!E19="","",'Setup'!E19) | H21: =IF(G21="","",'Setup'!G19) | I21: =IF(G21="","",SUMIFS($E$7:$E$86,$D$7:$D$86,G21)) | J21: =IF(G21="","",H21-I21) | K21: =IF(OR(G21="",H21=0),"",I21/H21) | L21: =IF(K21="","",REPT("█",ROUND(MIN(1,MAX(0,K21))*10,0))&REPT("░",10-ROUND(MIN(1,MAX(0,K21))*10,0)))
G22: =IF('Setup'!E20="","",'Setup'!E20) | H22: =IF(G22="","",'Setup'!G20) | I22: =IF(G22="","",SUMIFS($E$7:$E$86,$D$7:$D$86,G22)) | J22: =IF(G22="","",H22-I22) | K22: =IF(OR(G22="",H22=0),"",I22/H22) | L22: =IF(K22="","",REPT("█",ROUND(MIN(1,MAX(0,K22))*10,0))&REPT("░",10-ROUND(MIN(1,MAX(0,K22))*10,0)))
G23: =IF('Setup'!E21="","",'Setup'!E21) | H23: =IF(G23="","",'Setup'!G21) | I23: =IF(G23="","",SUMIFS($E$7:$E$86,$D$7:$D$86,G23)) | J23: =IF(G23="","",H23-I23) | K23: =IF(OR(G23="",H23=0),"",I23/H23) | L23: =IF(K23="","",REPT("█",ROUND(MIN(1,MAX(0,K23))*10,0))&REPT("░",10-ROUND(MIN(1,MAX(0,K23))*10,0)))
... G41: =IF('Setup'!E39="","",'Setup'!E39) | H41: =IF(G41="","",'Setup'!G39) | I41: =IF(G41="","",SUMIFS($E$7:$E$86,$D$7:$D$86,G41)) | J41: =IF(G41="","",H41-I41) | K41: =IF(OR(G41="",H41=0),"",I41/H41) | L41: =IF(K41="","",REPT("█",ROUND(MIN(1,MAX(0,K41))*10,0))&REPT("░",10-ROUND(MIN(1,MAX(0,K41))*10,0)))

Sheet September
B2: September
B3: Log what you spend. The summary on the right updates itself.
B4: Start here | D4: Dashboard | E4: Setup | F4: Months | G4: Bills | H4: Paycheck | I4: Debt | J4: Savings
B6: Date | C6: What | D6: Category | E6: Amount | G6: Income this month | H6: ='Setup'!$C$18 | I6: Type over this if your income was different
G7: Spent | H7: =SUM(E7:E86)
G8: Left over | H8: =H6-H7
G9: Saved and debt paid | H9: =SUMPRODUCT(SUMIFS($E$7:$E$86,$D$7:$D$86,'Setup'!$E$10:$E$39)*(('Setup'!$F$10:$F$39="Savings")+('Setup'!$F$10:$F$39="Debt")))
G11: Category | H11: Budget | I11: Spent | J11: Left | K11: Used
G12: =IF('Setup'!E10="","",'Setup'!E10) | H12: =IF(G12="","",'Setup'!G10) | I12: =IF(G12="","",SUMIFS($E$7:$E$86,$D$7:$D$86,G12)) | J12: =IF(G12="","",H12-I12) | K12: =IF(OR(G12="",H12=0),"",I12/H12) | L12: =IF(K12="","",REPT("█",ROUND(MIN(1,MAX(0,K12))*10,0))&REPT("░",10-ROUND(MIN(1,MAX(0,K12))*10,0)))
G13: =IF('Setup'!E11="","",'Setup'!E11) | H13: =IF(G13="","",'Setup'!G11) | I13: =IF(G13="","",SUMIFS($E$7:$E$86,$D$7:$D$86,G13)) | J13: =IF(G13="","",H13-I13) | K13: =IF(OR(G13="",H13=0),"",I13/H13) | L13: =IF(K13="","",REPT("█",ROUND(MIN(1,MAX(0,K13))*10,0))&REPT("░",10-ROUND(MIN(1,MAX(0,K13))*10,0)))
G14: =IF('Setup'!E12="","",'Setup'!E12) | H14: =IF(G14="","",'Setup'!G12) | I14: =IF(G14="","",SUMIFS($E$7:$E$86,$D$7:$D$86,G14)) | J14: =IF(G14="","",H14-I14) | K14: =IF(OR(G14="",H14=0),"",I14/H14) | L14: =IF(K14="","",REPT("█",ROUND(MIN(1,MAX(0,K14))*10,0))&REPT("░",10-ROUND(MIN(1,MAX(0,K14))*10,0)))
G15: =IF('Setup'!E13="","",'Setup'!E13) | H15: =IF(G15="","",'Setup'!G13) | I15: =IF(G15="","",SUMIFS($E$7:$E$86,$D$7:$D$86,G15)) | J15: =IF(G15="","",H15-I15) | K15: =IF(OR(G15="",H15=0),"",I15/H15) | L15: =IF(K15="","",REPT("█",ROUND(MIN(1,MAX(0,K15))*10,0))&REPT("░",10-ROUND(MIN(1,MAX(0,K15))*10,0)))
G16: =IF('Setup'!E14="","",'Setup'!E14) | H16: =IF(G16="","",'Setup'!G14) | I16: =IF(G16="","",SUMIFS($E$7:$E$86,$D$7:$D$86,G16)) | J16: =IF(G16="","",H16-I16) | K16: =IF(OR(G16="",H16=0),"",I16/H16) | L16: =IF(K16="","",REPT("█",ROUND(MIN(1,MAX(0,K16))*10,0))&REPT("░",10-ROUND(MIN(1,MAX(0,K16))*10,0)))
G17: =IF('Setup'!E15="","",'Setup'!E15) | H17: =IF(G17="","",'Setup'!G15) | I17: =IF(G17="","",SUMIFS($E$7:$E$86,$D$7:$D$86,G17)) | J17: =IF(G17="","",H17-I17) | K17: =IF(OR(G17="",H17=0),"",I17/H17) | L17: =IF(K17="","",REPT("█",ROUND(MIN(1,MAX(0,K17))*10,0))&REPT("░",10-ROUND(MIN(1,MAX(0,K17))*10,0)))
G18: =IF('Setup'!E16="","",'Setup'!E16) | H18: =IF(G18="","",'Setup'!G16) | I18: =IF(G18="","",SUMIFS($E$7:$E$86,$D$7:$D$86,G18)) | J18: =IF(G18="","",H18-I18) | K18: =IF(OR(G18="",H18=0),"",I18/H18) | L18: =IF(K18="","",REPT("█",ROUND(MIN(1,MAX(0,K18))*10,0))&REPT("░",10-ROUND(MIN(1,MAX(0,K18))*10,0)))
G19: =IF('Setup'!E17="","",'Setup'!E17) | H19: =IF(G19="","",'Setup'!G17) | I19: =IF(G19="","",SUMIFS($E$7:$E$86,$D$7:$D$86,G19)) | J19: =IF(G19="","",H19-I19) | K19: =IF(OR(G19="",H19=0),"",I19/H19) | L19: =IF(K19="","",REPT("█",ROUND(MIN(1,MAX(0,K19))*10,0))&REPT("░",10-ROUND(MIN(1,MAX(0,K19))*10,0)))
G20: =IF('Setup'!E18="","",'Setup'!E18) | H20: =IF(G20="","",'Setup'!G18) | I20: =IF(G20="","",SUMIFS($E$7:$E$86,$D$7:$D$86,G20)) | J20: =IF(G20="","",H20-I20) | K20: =IF(OR(G20="",H20=0),"",I20/H20) | L20: =IF(K20="","",REPT("█",ROUND(MIN(1,MAX(0,K20))*10,0))&REPT("░",10-ROUND(MIN(1,MAX(0,K20))*10,0)))
G21: =IF('Setup'!E19="","",'Setup'!E19) | H21: =IF(G21="","",'Setup'!G19) | I21: =IF(G21="","",SUMIFS($E$7:$E$86,$D$7:$D$86,G21)) | J21: =IF(G21="","",H21-I21) | K21: =IF(OR(G21="",H21=0),"",I21/H21) | L21: =IF(K21="","",REPT("█",ROUND(MIN(1,MAX(0,K21))*10,0))&REPT("░",10-ROUND(MIN(1,MAX(0,K21))*10,0)))
G22: =IF('Setup'!E20="","",'Setup'!E20) | H22: =IF(G22="","",'Setup'!G20) | I22: =IF(G22="","",SUMIFS($E$7:$E$86,$D$7:$D$86,G22)) | J22: =IF(G22="","",H22-I22) | K22: =IF(OR(G22="",H22=0),"",I22/H22) | L22: =IF(K22="","",REPT("█",ROUND(MIN(1,MAX(0,K22))*10,0))&REPT("░",10-ROUND(MIN(1,MAX(0,K22))*10,0)))
G23: =IF('Setup'!E21="","",'Setup'!E21) | H23: =IF(G23="","",'Setup'!G21) | I23: =IF(G23="","",SUMIFS($E$7:$E$86,$D$7:$D$86,G23)) | J23: =IF(G23="","",H23-I23) | K23: =IF(OR(G23="",H23=0),"",I23/H23) | L23: =IF(K23="","",REPT("█",ROUND(MIN(1,MAX(0,K23))*10,0))&REPT("░",10-ROUND(MIN(1,MAX(0,K23))*10,0)))
... G41: =IF('Setup'!E39="","",'Setup'!E39) | H41: =IF(G41="","",'Setup'!G39) | I41: =IF(G41="","",SUMIFS($E$7:$E$86,$D$7:$D$86,G41)) | J41: =IF(G41="","",H41-I41) | K41: =IF(OR(G41="",H41=0),"",I41/H41) | L41: =IF(K41="","",REPT("█",ROUND(MIN(1,MAX(0,K41))*10,0))&REPT("░",10-ROUND(MIN(1,MAX(0,K41))*10,0)))

Sheet October
B2: October
B3: Log what you spend. The summary on the right updates itself.
B4: Start here | D4: Dashboard | E4: Setup | F4: Months | G4: Bills | H4: Paycheck | I4: Debt | J4: Savings
B6: Date | C6: What | D6: Category | E6: Amount | G6: Income this month | H6: ='Setup'!$C$18 | I6: Type over this if your income was different
G7: Spent | H7: =SUM(E7:E86)
G8: Left over | H8: =H6-H7
G9: Saved and debt paid | H9: =SUMPRODUCT(SUMIFS($E$7:$E$86,$D$7:$D$86,'Setup'!$E$10:$E$39)*(('Setup'!$F$10:$F$39="Savings")+('Setup'!$F$10:$F$39="Debt")))
G11: Category | H11: Budget | I11: Spent | J11: Left | K11: Used
G12: =IF('Setup'!E10="","",'Setup'!E10) | H12: =IF(G12="","",'Setup'!G10) | I12: =IF(G12="","",SUMIFS($E$7:$E$86,$D$7:$D$86,G12)) | J12: =IF(G12="","",H12-I12) | K12: =IF(OR(G12="",H12=0),"",I12/H12) | L12: =IF(K12="","",REPT("█",ROUND(MIN(1,MAX(0,K12))*10,0))&REPT("░",10-ROUND(MIN(1,MAX(0,K12))*10,0)))
G13: =IF('Setup'!E11="","",'Setup'!E11) | H13: =IF(G13="","",'Setup'!G11) | I13: =IF(G13="","",SUMIFS($E$7:$E$86,$D$7:$D$86,G13)) | J13: =IF(G13="","",H13-I13) | K13: =IF(OR(G13="",H13=0),"",I13/H13) | L13: =IF(K13="","",REPT("█",ROUND(MIN(1,MAX(0,K13))*10,0))&REPT("░",10-ROUND(MIN(1,MAX(0,K13))*10,0)))
G14: =IF('Setup'!E12="","",'Setup'!E12) | H14: =IF(G14="","",'Setup'!G12) | I14: =IF(G14="","",SUMIFS($E$7:$E$86,$D$7:$D$86,G14)) | J14: =IF(G14="","",H14-I14) | K14: =IF(OR(G14="",H14=0),"",I14/H14) | L14: =IF(K14="","",REPT("█",ROUND(MIN(1,MAX(0,K14))*10,0))&REPT("░",10-ROUND(MIN(1,MAX(0,K14))*10,0)))
G15: =IF('Setup'!E13="","",'Setup'!E13) | H15: =IF(G15="","",'Setup'!G13) | I15: =IF(G15="","",SUMIFS($E$7:$E$86,$D$7:$D$86,G15)) | J15: =IF(G15="","",H15-I15) | K15: =IF(OR(G15="",H15=0),"",I15/H15) | L15: =IF(K15="","",REPT("█",ROUND(MIN(1,MAX(0,K15))*10,0))&REPT("░",10-ROUND(MIN(1,MAX(0,K15))*10,0)))
G16: =IF('Setup'!E14="","",'Setup'!E14) | H16: =IF(G16="","",'Setup'!G14) | I16: =IF(G16="","",SUMIFS($E$7:$E$86,$D$7:$D$86,G16)) | J16: =IF(G16="","",H16-I16) | K16: =IF(OR(G16="",H16=0),"",I16/H16) | L16: =IF(K16="","",REPT("█",ROUND(MIN(1,MAX(0,K16))*10,0))&REPT("░",10-ROUND(MIN(1,MAX(0,K16))*10,0)))
G17: =IF('Setup'!E15="","",'Setup'!E15) | H17: =IF(G17="","",'Setup'!G15) | I17: =IF(G17="","",SUMIFS($E$7:$E$86,$D$7:$D$86,G17)) | J17: =IF(G17="","",H17-I17) | K17: =IF(OR(G17="",H17=0),"",I17/H17) | L17: =IF(K17="","",REPT("█",ROUND(MIN(1,MAX(0,K17))*10,0))&REPT("░",10-ROUND(MIN(1,MAX(0,K17))*10,0)))
G18: =IF('Setup'!E16="","",'Setup'!E16) | H18: =IF(G18="","",'Setup'!G16) | I18: =IF(G18="","",SUMIFS($E$7:$E$86,$D$7:$D$86,G18)) | J18: =IF(G18="","",H18-I18) | K18: =IF(OR(G18="",H18=0),"",I18/H18) | L18: =IF(K18="","",REPT("█",ROUND(MIN(1,MAX(0,K18))*10,0))&REPT("░",10-ROUND(MIN(1,MAX(0,K18))*10,0)))
G19: =IF('Setup'!E17="","",'Setup'!E17) | H19: =IF(G19="","",'Setup'!G17) | I19: =IF(G19="","",SUMIFS($E$7:$E$86,$D$7:$D$86,G19)) | J19: =IF(G19="","",H19-I19) | K19: =IF(OR(G19="",H19=0),"",I19/H19) | L19: =IF(K19="","",REPT("█",ROUND(MIN(1,MAX(0,K19))*10,0))&REPT("░",10-ROUND(MIN(1,MAX(0,K19))*10,0)))
G20: =IF('Setup'!E18="","",'Setup'!E18) | H20: =IF(G20="","",'Setup'!G18) | I20: =IF(G20="","",SUMIFS($E$7:$E$86,$D$7:$D$86,G20)) | J20: =IF(G20="","",H20-I20) | K20: =IF(OR(G20="",H20=0),"",I20/H20) | L20: =IF(K20="","",REPT("█",ROUND(MIN(1,MAX(0,K20))*10,0))&REPT("░",10-ROUND(MIN(1,MAX(0,K20))*10,0)))
G21: =IF('Setup'!E19="","",'Setup'!E19) | H21: =IF(G21="","",'Setup'!G19) | I21: =IF(G21="","",SUMIFS($E$7:$E$86,$D$7:$D$86,G21)) | J21: =IF(G21="","",H21-I21) | K21: =IF(OR(G21="",H21=0),"",I21/H21) | L21: =IF(K21="","",REPT("█",ROUND(MIN(1,MAX(0,K21))*10,0))&REPT("░",10-ROUND(MIN(1,MAX(0,K21))*10,0)))
G22: =IF('Setup'!E20="","",'Setup'!E20) | H22: =IF(G22="","",'Setup'!G20) | I22: =IF(G22="","",SUMIFS($E$7:$E$86,$D$7:$D$86,G22)) | J22: =IF(G22="","",H22-I22) | K22: =IF(OR(G22="",H22=0),"",I22/H22) | L22: =IF(K22="","",REPT("█",ROUND(MIN(1,MAX(0,K22))*10,0))&REPT("░",10-ROUND(MIN(1,MAX(0,K22))*10,0)))
G23: =IF('Setup'!E21="","",'Setup'!E21) | H23: =IF(G23="","",'Setup'!G21) | I23: =IF(G23="","",SUMIFS($E$7:$E$86,$D$7:$D$86,G23)) | J23: =IF(G23="","",H23-I23) | K23: =IF(OR(G23="",H23=0),"",I23/H23) | L23: =IF(K23="","",REPT("█",ROUND(MIN(1,MAX(0,K23))*10,0))&REPT("░",10-ROUND(MIN(1,MAX(0,K23))*10,0)))
... G41: =IF('Setup'!E39="","",'Setup'!E39) | H41: =IF(G41="","",'Setup'!G39) | I41: =IF(G41="","",SUMIFS($E$7:$E$86,$D$7:$D$86,G41)) | J41: =IF(G41="","",H41-I41) | K41: =IF(OR(G41="",H41=0),"",I41/H41) | L41: =IF(K41="","",REPT("█",ROUND(MIN(1,MAX(0,K41))*10,0))&REPT("░",10-ROUND(MIN(1,MAX(0,K41))*10,0)))

Sheet November
B2: November
B3: Log what you spend. The summary on the right updates itself.
B4: Start here | D4: Dashboard | E4: Setup | F4: Months | G4: Bills | H4: Paycheck | I4: Debt | J4: Savings
B6: Date | C6: What | D6: Category | E6: Amount | G6: Income this month | H6: ='Setup'!$C$18 | I6: Type over this if your income was different
G7: Spent | H7: =SUM(E7:E86)
G8: Left over | H8: =H6-H7
G9: Saved and debt paid | H9: =SUMPRODUCT(SUMIFS($E$7:$E$86,$D$7:$D$86,'Setup'!$E$10:$E$39)*(('Setup'!$F$10:$F$39="Savings")+('Setup'!$F$10:$F$39="Debt")))
G11: Category | H11: Budget | I11: Spent | J11: Left | K11: Used
G12: =IF('Setup'!E10="","",'Setup'!E10) | H12: =IF(G12="","",'Setup'!G10) | I12: =IF(G12="","",SUMIFS($E$7:$E$86,$D$7:$D$86,G12)) | J12: =IF(G12="","",H12-I12) | K12: =IF(OR(G12="",H12=0),"",I12/H12) | L12: =IF(K12="","",REPT("█",ROUND(MIN(1,MAX(0,K12))*10,0))&REPT("░",10-ROUND(MIN(1,MAX(0,K12))*10,0)))
G13: =IF('Setup'!E11="","",'Setup'!E11) | H13: =IF(G13="","",'Setup'!G11) | I13: =IF(G13="","",SUMIFS($E$7:$E$86,$D$7:$D$86,G13)) | J13: =IF(G13="","",H13-I13) | K13: =IF(OR(G13="",H13=0),"",I13/H13) | L13: =IF(K13="","",REPT("█",ROUND(MIN(1,MAX(0,K13))*10,0))&REPT("░",10-ROUND(MIN(1,MAX(0,K13))*10,0)))
G14: =IF('Setup'!E12="","",'Setup'!E12) | H14: =IF(G14="","",'Setup'!G12) | I14: =IF(G14="","",SUMIFS($E$7:$E$86,$D$7:$D$86,G14)) | J14: =IF(G14="","",H14-I14) | K14: =IF(OR(G14="",H14=0),"",I14/H14) | L14: =IF(K14="","",REPT("█",ROUND(MIN(1,MAX(0,K14))*10,0))&REPT("░",10-ROUND(MIN(1,MAX(0,K14))*10,0)))
G15: =IF('Setup'!E13="","",'Setup'!E13) | H15: =IF(G15="","",'Setup'!G13) | I15: =IF(G15="","",SUMIFS($E$7:$E$86,$D$7:$D$86,G15)) | J15: =IF(G15="","",H15-I15) | K15: =IF(OR(G15="",H15=0),"",I15/H15) | L15: =IF(K15="","",REPT("█",ROUND(MIN(1,MAX(0,K15))*10,0))&REPT("░",10-ROUND(MIN(1,MAX(0,K15))*10,0)))
G16: =IF('Setup'!E14="","",'Setup'!E14) | H16: =IF(G16="","",'Setup'!G14) | I16: =IF(G16="","",SUMIFS($E$7:$E$86,$D$7:$D$86,G16)) | J16: =IF(G16="","",H16-I16) | K16: =IF(OR(G16="",H16=0),"",I16/H16) | L16: =IF(K16="","",REPT("█",ROUND(MIN(1,MAX(0,K16))*10,0))&REPT("░",10-ROUND(MIN(1,MAX(0,K16))*10,0)))
G17: =IF('Setup'!E15="","",'Setup'!E15) | H17: =IF(G17="","",'Setup'!G15) | I17: =IF(G17="","",SUMIFS($E$7:$E$86,$D$7:$D$86,G17)) | J17: =IF(G17="","",H17-I17) | K17: =IF(OR(G17="",H17=0),"",I17/H17) | L17: =IF(K17="","",REPT("█",ROUND(MIN(1,MAX(0,K17))*10,0))&REPT("░",10-ROUND(MIN(1,MAX(0,K17))*10,0)))
G18: =IF('Setup'!E16="","",'Setup'!E16) | H18: =IF(G18="","",'Setup'!G16) | I18: =IF(G18="","",SUMIFS($E$7:$E$86,$D$7:$D$86,G18)) | J18: =IF(G18="","",H18-I18) | K18: =IF(OR(G18="",H18=0),"",I18/H18) | L18: =IF(K18="","",REPT("█",ROUND(MIN(1,MAX(0,K18))*10,0))&REPT("░",10-ROUND(MIN(1,MAX(0,K18))*10,0)))
G19: =IF('Setup'!E17="","",'Setup'!E17) | H19: =IF(G19="","",'Setup'!G17) | I19: =IF(G19="","",SUMIFS($E$7:$E$86,$D$7:$D$86,G19)) | J19: =IF(G19="","",H19-I19) | K19: =IF(OR(G19="",H19=0),"",I19/H19) | L19: =IF(K19="","",REPT("█",ROUND(MIN(1,MAX(0,K19))*10,0))&REPT("░",10-ROUND(MIN(1,MAX(0,K19))*10,0)))
G20: =IF('Setup'!E18="","",'Setup'!E18) | H20: =IF(G20="","",'Setup'!G18) | I20: =IF(G20="","",SUMIFS($E$7:$E$86,$D$7:$D$86,G20)) | J20: =IF(G20="","",H20-I20) | K20: =IF(OR(G20="",H20=0),"",I20/H20) | L20: =IF(K20="","",REPT("█",ROUND(MIN(1,MAX(0,K20))*10,0))&REPT("░",10-ROUND(MIN(1,MAX(0,K20))*10,0)))
G21: =IF('Setup'!E19="","",'Setup'!E19) | H21: =IF(G21="","",'Setup'!G19) | I21: =IF(G21="","",SUMIFS($E$7:$E$86,$D$7:$D$86,G21)) | J21: =IF(G21="","",H21-I21) | K21: =IF(OR(G21="",H21=0),"",I21/H21) | L21: =IF(K21="","",REPT("█",ROUND(MIN(1,MAX(0,K21))*10,0))&REPT("░",10-ROUND(MIN(1,MAX(0,K21))*10,0)))
G22: =IF('Setup'!E20="","",'Setup'!E20) | H22: =IF(G22="","",'Setup'!G20) | I22: =IF(G22="","",SUMIFS($E$7:$E$86,$D$7:$D$86,G22)) | J22: =IF(G22="","",H22-I22) | K22: =IF(OR(G22="",H22=0),"",I22/H22) | L22: =IF(K22="","",REPT("█",ROUND(MIN(1,MAX(0,K22))*10,0))&REPT("░",10-ROUND(MIN(1,MAX(0,K22))*10,0)))
G23: =IF('Setup'!E21="","",'Setup'!E21) | H23: =IF(G23="","",'Setup'!G21) | I23: =IF(G23="","",SUMIFS($E$7:$E$86,$D$7:$D$86,G23)) | J23: =IF(G23="","",H23-I23) | K23: =IF(OR(G23="",H23=0),"",I23/H23) | L23: =IF(K23="","",REPT("█",ROUND(MIN(1,MAX(0,K23))*10,0))&REPT("░",10-ROUND(MIN(1,MAX(0,K23))*10,0)))
... G41: =IF('Setup'!E39="","",'Setup'!E39) | H41: =IF(G41="","",'Setup'!G39) | I41: =IF(G41="","",SUMIFS($E$7:$E$86,$D$7:$D$86,G41)) | J41: =IF(G41="","",H41-I41) | K41: =IF(OR(G41="",H41=0),"",I41/H41) | L41: =IF(K41="","",REPT("█",ROUND(MIN(1,MAX(0,K41))*10,0))&REPT("░",10-ROUND(MIN(1,MAX(0,K41))*10,0)))

Sheet December
B2: December
B3: Log what you spend. The summary on the right updates itself.
B4: Start here | D4: Dashboard | E4: Setup | F4: Months | G4: Bills | H4: Paycheck | I4: Debt | J4: Savings
B6: Date | C6: What | D6: Category | E6: Amount | G6: Income this month | H6: ='Setup'!$C$18 | I6: Type over this if your income was different
G7: Spent | H7: =SUM(E7:E86)
G8: Left over | H8: =H6-H7
G9: Saved and debt paid | H9: =SUMPRODUCT(SUMIFS($E$7:$E$86,$D$7:$D$86,'Setup'!$E$10:$E$39)*(('Setup'!$F$10:$F$39="Savings")+('Setup'!$F$10:$F$39="Debt")))
G11: Category | H11: Budget | I11: Spent | J11: Left | K11: Used
G12: =IF('Setup'!E10="","",'Setup'!E10) | H12: =IF(G12="","",'Setup'!G10) | I12: =IF(G12="","",SUMIFS($E$7:$E$86,$D$7:$D$86,G12)) | J12: =IF(G12="","",H12-I12) | K12: =IF(OR(G12="",H12=0),"",I12/H12) | L12: =IF(K12="","",REPT("█",ROUND(MIN(1,MAX(0,K12))*10,0))&REPT("░",10-ROUND(MIN(1,MAX(0,K12))*10,0)))
G13: =IF('Setup'!E11="","",'Setup'!E11) | H13: =IF(G13="","",'Setup'!G11) | I13: =IF(G13="","",SUMIFS($E$7:$E$86,$D$7:$D$86,G13)) | J13: =IF(G13="","",H13-I13) | K13: =IF(OR(G13="",H13=0),"",I13/H13) | L13: =IF(K13="","",REPT("█",ROUND(MIN(1,MAX(0,K13))*10,0))&REPT("░",10-ROUND(MIN(1,MAX(0,K13))*10,0)))
G14: =IF('Setup'!E12="","",'Setup'!E12) | H14: =IF(G14="","",'Setup'!G12) | I14: =IF(G14="","",SUMIFS($E$7:$E$86,$D$7:$D$86,G14)) | J14: =IF(G14="","",H14-I14) | K14: =IF(OR(G14="",H14=0),"",I14/H14) | L14: =IF(K14="","",REPT("█",ROUND(MIN(1,MAX(0,K14))*10,0))&REPT("░",10-ROUND(MIN(1,MAX(0,K14))*10,0)))
G15: =IF('Setup'!E13="","",'Setup'!E13) | H15: =IF(G15="","",'Setup'!G13) | I15: =IF(G15="","",SUMIFS($E$7:$E$86,$D$7:$D$86,G15)) | J15: =IF(G15="","",H15-I15) | K15: =IF(OR(G15="",H15=0),"",I15/H15) | L15: =IF(K15="","",REPT("█",ROUND(MIN(1,MAX(0,K15))*10,0))&REPT("░",10-ROUND(MIN(1,MAX(0,K15))*10,0)))
G16: =IF('Setup'!E14="","",'Setup'!E14) | H16: =IF(G16="","",'Setup'!G14) | I16: =IF(G16="","",SUMIFS($E$7:$E$86,$D$7:$D$86,G16)) | J16: =IF(G16="","",H16-I16) | K16: =IF(OR(G16="",H16=0),"",I16/H16) | L16: =IF(K16="","",REPT("█",ROUND(MIN(1,MAX(0,K16))*10,0))&REPT("░",10-ROUND(MIN(1,MAX(0,K16))*10,0)))
G17: =IF('Setup'!E15="","",'Setup'!E15) | H17: =IF(G17="","",'Setup'!G15) | I17: =IF(G17="","",SUMIFS($E$7:$E$86,$D$7:$D$86,G17)) | J17: =IF(G17="","",H17-I17) | K17: =IF(OR(G17="",H17=0),"",I17/H17) | L17: =IF(K17="","",REPT("█",ROUND(MIN(1,MAX(0,K17))*10,0))&REPT("░",10-ROUND(MIN(1,MAX(0,K17))*10,0)))
G18: =IF('Setup'!E16="","",'Setup'!E16) | H18: =IF(G18="","",'Setup'!G16) | I18: =IF(G18="","",SUMIFS($E$7:$E$86,$D$7:$D$86,G18)) | J18: =IF(G18="","",H18-I18) | K18: =IF(OR(G18="",H18=0),"",I18/H18) | L18: =IF(K18="","",REPT("█",ROUND(MIN(1,MAX(0,K18))*10,0))&REPT("░",10-ROUND(MIN(1,MAX(0,K18))*10,0)))
G19: =IF('Setup'!E17="","",'Setup'!E17) | H19: =IF(G19="","",'Setup'!G17) | I19: =IF(G19="","",SUMIFS($E$7:$E$86,$D$7:$D$86,G19)) | J19: =IF(G19="","",H19-I19) | K19: =IF(OR(G19="",H19=0),"",I19/H19) | L19: =IF(K19="","",REPT("█",ROUND(MIN(1,MAX(0,K19))*10,0))&REPT("░",10-ROUND(MIN(1,MAX(0,K19))*10,0)))
G20: =IF('Setup'!E18="","",'Setup'!E18) | H20: =IF(G20="","",'Setup'!G18) | I20: =IF(G20="","",SUMIFS($E$7:$E$86,$D$7:$D$86,G20)) | J20: =IF(G20="","",H20-I20) | K20: =IF(OR(G20="",H20=0),"",I20/H20) | L20: =IF(K20="","",REPT("█",ROUND(MIN(1,MAX(0,K20))*10,0))&REPT("░",10-ROUND(MIN(1,MAX(0,K20))*10,0)))
G21: =IF('Setup'!E19="","",'Setup'!E19) | H21: =IF(G21="","",'Setup'!G19) | I21: =IF(G21="","",SUMIFS($E$7:$E$86,$D$7:$D$86,G21)) | J21: =IF(G21="","",H21-I21) | K21: =IF(OR(G21="",H21=0),"",I21/H21) | L21: =IF(K21="","",REPT("█",ROUND(MIN(1,MAX(0,K21))*10,0))&REPT("░",10-ROUND(MIN(1,MAX(0,K21))*10,0)))
G22: =IF('Setup'!E20="","",'Setup'!E20) | H22: =IF(G22="","",'Setup'!G20) | I22: =IF(G22="","",SUMIFS($E$7:$E$86,$D$7:$D$86,G22)) | J22: =IF(G22="","",H22-I22) | K22: =IF(OR(G22="",H22=0),"",I22/H22) | L22: =IF(K22="","",REPT("█",ROUND(MIN(1,MAX(0,K22))*10,0))&REPT("░",10-ROUND(MIN(1,MAX(0,K22))*10,0)))
G23: =IF('Setup'!E21="","",'Setup'!E21) | H23: =IF(G23="","",'Setup'!G21) | I23: =IF(G23="","",SUMIFS($E$7:$E$86,$D$7:$D$86,G23)) | J23: =IF(G23="","",H23-I23) | K23: =IF(OR(G23="",H23=0),"",I23/H23) | L23: =IF(K23="","",REPT("█",ROUND(MIN(1,MAX(0,K23))*10,0))&REPT("░",10-ROUND(MIN(1,MAX(0,K23))*10,0)))
... G41: =IF('Setup'!E39="","",'Setup'!E39) | H41: =IF(G41="","",'Setup'!G39) | I41: =IF(G41="","",SUMIFS($E$7:$E$86,$D$7:$D$86,G41)) | J41: =IF(G41="","",H41-I41) | K41: =IF(OR(G41="",H41=0),"",I41/H41) | L41: =IF(K41="","",REPT("█",ROUND(MIN(1,MAX(0,K41))*10,0))&REPT("░",10-ROUND(MIN(1,MAX(0,K41))*10,0)))

Sheet Bills
B2: Bills
B3: Mark each bill paid with a ✓ from the dropdown.
B4: Start here | C4: Dashboard | E4: Setup | F4: Months | H4: Bills | J4: Paycheck | L4: Debt | N4: Savings
B6: Bill | C6: Due day | D6: Amount | E6: Autopay | F6: Jan | G6: Feb | H6: Mar | I6: Apr | J6: May | K6: Jun | L6: Jul | M6: Aug | N6: Sep | O6: Oct | P6: Nov | Q6: Dec
B7: Rent | C7: 1 | D7: 1400 | E7: Yes
B8: Phone and internet | C8: 14 | D8: 95 | E8: Yes
B9: Streaming | C9: 18 | D9: 15.99 | E9: Yes
B10: Car insurance | C10: 20 | D10: 160 | E10: No
B11: Electric | C11: 22 | D11: 90 | E11: No
B12: Credit card | C12: 25 | D12: 150 | E12: No
B32: Total per month | D32: =SUM(D7:D31)

Sheet Paycheck plan
B2: Paycheck plan
B3: Paid weekly or every two weeks? See which bills each paycheck covers. Paid monthly? Skip this tab.
B4: Start here | C4: Dashboard | D4: Setup | E4: Months | F4: Bills | G4: Paycheck | H4: Debt | I4: Savings
B6: Next payday | C6: =DATE(Year,1,1)+MOD(6-WEEKDAY(DATE(Year,1,1)),7)
B7: How often | C7: Every 2 weeks
B8: Usual paycheck | C8: =ROUND('Setup'!$C$10*12/CHOOSE(MATCH($C$7,{"Weekly","Every 2 weeks","Twice a month","Monthly"},0),52,26,24,12),2) | D8: Starts from your first income line in Setup. Type your real take-home pay.
B10: Payday | C10: Paycheck | D10: Bills due before next payday | E10: Left from this paycheck | F10: Next payday
B11: =$C$6 | C11: =IF(B11="","",$C$8) | D11: =IF(B11="","",SUMPRODUCT(('Bills'!$C$7:$C$31<>"")*(DATE(YEAR(B11),MONTH(B11)+(DAY(B11)>'Bills'!$C$7:$C$31),'Bills'!$C$7:$C$31)<F11)*'Bills'!$D$7:$D$31)) | E11: =IF(B11="","",C11-D11) | F11: =IF(B11="","",CHOOSE(MATCH($C$7,{"Weekly","Every 2 weeks","Twice a month","Monthly"},0),B11+7,B11+14,IF(DAY(B11)<15,DATE(YEAR(B11),MONTH(B11),15),DATE(YEAR(B11),MONTH(B11)+1,1)),EDATE(B11,1)))
B12: =IF(F11="","",IF(F11>DATE(Year,12,31),"",F11)) | C12: =IF(B12="","",$C$8) | D12: =IF(B12="","",SUMPRODUCT(('Bills'!$C$7:$C$31<>"")*(DATE(YEAR(B12),MONTH(B12)+(DAY(B12)>'Bills'!$C$7:$C$31),'Bills'!$C$7:$C$31)<F12)*'Bills'!$D$7:$D$31)) | E12: =IF(B12="","",C12-D12) | F12: =IF(B12="","",CHOOSE(MATCH($C$7,{"Weekly","Every 2 weeks","Twice a month","Monthly"},0),B12+7,B12+14,IF(DAY(B12)<15,DATE(YEAR(B12),MONTH(B12),15),DATE(YEAR(B12),MONTH(B12)+1,1)),EDATE(B12,1)))
B13: =IF(F12="","",IF(F12>DATE(Year,12,31),"",F12)) | C13: =IF(B13="","",$C$8) | D13: =IF(B13="","",SUMPRODUCT(('Bills'!$C$7:$C$31<>"")*(DATE(YEAR(B13),MONTH(B13)+(DAY(B13)>'Bills'!$C$7:$C$31),'Bills'!$C$7:$C$31)<F13)*'Bills'!$D$7:$D$31)) | E13: =IF(B13="","",C13-D13) | F13: =IF(B13="","",CHOOSE(MATCH($C$7,{"Weekly","Every 2 weeks","Twice a month","Monthly"},0),B13+7,B13+14,IF(DAY(B13)<15,DATE(YEAR(B13),MONTH(B13),15),DATE(YEAR(B13),MONTH(B13)+1,1)),EDATE(B13,1)))
B14: =IF(F13="","",IF(F13>DATE(Year,12,31),"",F13)) | C14: =IF(B14="","",$C$8) | D14: =IF(B14="","",SUMPRODUCT(('Bills'!$C$7:$C$31<>"")*(DATE(YEAR(B14),MONTH(B14)+(DAY(B14)>'Bills'!$C$7:$C$31),'Bills'!$C$7:$C$31)<F14)*'Bills'!$D$7:$D$31)) | E14: =IF(B14="","",C14-D14) | F14: =IF(B14="","",CHOOSE(MATCH($C$7,{"Weekly","Every 2 weeks","Twice a month","Monthly"},0),B14+7,B14+14,IF(DAY(B14)<15,DATE(YEAR(B14),MONTH(B14),15),DATE(YEAR(B14),MONTH(B14)+1,1)),EDATE(B14,1)))
B15: =IF(F14="","",IF(F14>DATE(Year,12,31),"",F14)) | C15: =IF(B15="","",$C$8) | D15: =IF(B15="","",SUMPRODUCT(('Bills'!$C$7:$C$31<>"")*(DATE(YEAR(B15),MONTH(B15)+(DAY(B15)>'Bills'!$C$7:$C$31),'Bills'!$C$7:$C$31)<F15)*'Bills'!$D$7:$D$31)) | E15: =IF(B15="","",C15-D15) | F15: =IF(B15="","",CHOOSE(MATCH($C$7,{"Weekly","Every 2 weeks","Twice a month","Monthly"},0),B15+7,B15+14,IF(DAY(B15)<15,DATE(YEAR(B15),MONTH(B15),15),DATE(YEAR(B15),MONTH(B15)+1,1)),EDATE(B15,1)))
B16: =IF(F15="","",IF(F15>DATE(Year,12,31),"",F15)) | C16: =IF(B16="","",$C$8) | D16: =IF(B16="","",SUMPRODUCT(('Bills'!$C$7:$C$31<>"")*(DATE(YEAR(B16),MONTH(B16)+(DAY(B16)>'Bills'!$C$7:$C$31),'Bills'!$C$7:$C$31)<F16)*'Bills'!$D$7:$D$31)) | E16: =IF(B16="","",C16-D16) | F16: =IF(B16="","",CHOOSE(MATCH($C$7,{"Weekly","Every 2 weeks","Twice a month","Monthly"},0),B16+7,B16+14,IF(DAY(B16)<15,DATE(YEAR(B16),MONTH(B16),15),DATE(YEAR(B16),MONTH(B16)+1,1)),EDATE(B16,1)))
B17: =IF(F16="","",IF(F16>DATE(Year,12,31),"",F16)) | C17: =IF(B17="","",$C$8) | D17: =IF(B17="","",SUMPRODUCT(('Bills'!$C$7:$C$31<>"")*(DATE(YEAR(B17),MONTH(B17)+(DAY(B17)>'Bills'!$C$7:$C$31),'Bills'!$C$7:$C$31)<F17)*'Bills'!$D$7:$D$31)) | E17: =IF(B17="","",C17-D17) | F17: =IF(B17="","",CHOOSE(MATCH($C$7,{"Weekly","Every 2 weeks","Twice a month","Monthly"},0),B17+7,B17+14,IF(DAY(B17)<15,DATE(YEAR(B17),MONTH(B17),15),DATE(YEAR(B17),MONTH(B17)+1,1)),EDATE(B17,1)))
B18: =IF(F17="","",IF(F17>DATE(Year,12,31),"",F17)) | C18: =IF(B18="","",$C$8) | D18: =IF(B18="","",SUMPRODUCT(('Bills'!$C$7:$C$31<>"")*(DATE(YEAR(B18),MONTH(B18)+(DAY(B18)>'Bills'!$C$7:$C$31),'Bills'!$C$7:$C$31)<F18)*'Bills'!$D$7:$D$31)) | E18: =IF(B18="","",C18-D18) | F18: =IF(B18="","",CHOOSE(MATCH($C$7,{"Weekly","Every 2 weeks","Twice a month","Monthly"},0),B18+7,B18+14,IF(DAY(B18)<15,DATE(YEAR(B18),MONTH(B18),15),DATE(YEAR(B18),MONTH(B18)+1,1)),EDATE(B18,1)))
B19: =IF(F18="","",IF(F18>DATE(Year,12,31),"",F18)) | C19: =IF(B19="","",$C$8) | D19: =IF(B19="","",SUMPRODUCT(('Bills'!$C$7:$C$31<>"")*(DATE(YEAR(B19),MONTH(B19)+(DAY(B19)>'Bills'!$C$7:$C$31),'Bills'!$C$7:$C$31)<F19)*'Bills'!$D$7:$D$31)) | E19: =IF(B19="","",C19-D19) | F19: =IF(B19="","",CHOOSE(MATCH($C$7,{"Weekly","Every 2 weeks","Twice a month","Monthly"},0),B19+7,B19+14,IF(DAY(B19)<15,DATE(YEAR(B19),MONTH(B19),15),DATE(YEAR(B19),MONTH(B19)+1,1)),EDATE(B19,1)))
B20: =IF(F19="","",IF(F19>DATE(Year,12,31),"",F19)) | C20: =IF(B20="","",$C$8) | D20: =IF(B20="","",SUMPRODUCT(('Bills'!$C$7:$C$31<>"")*(DATE(YEAR(B20),MONTH(B20)+(DAY(B20)>'Bills'!$C$7:$C$31),'Bills'!$C$7:$C$31)<F20)*'Bills'!$D$7:$D$31)) | E20: =IF(B20="","",C20-D20) | F20: =IF(B20="","",CHOOSE(MATCH($C$7,{"Weekly","Every 2 weeks","Twice a month","Monthly"},0),B20+7,B20+14,IF(DAY(B20)<15,DATE(YEAR(B20),MONTH(B20),15),DATE(YEAR(B20),MONTH(B20)+1,1)),EDATE(B20,1)))
B21: =IF(F20="","",IF(F20>DATE(Year,12,31),"",F20)) | C21: =IF(B21="","",$C$8) | D21: =IF(B21="","",SUMPRODUCT(('Bills'!$C$7:$C$31<>"")*(DATE(YEAR(B21),MONTH(B21)+(DAY(B21)>'Bills'!$C$7:$C$31),'Bills'!$C$7:$C$31)<F21)*'Bills'!$D$7:$D$31)) | E21: =IF(B21="","",C21-D21) | F21: =IF(B21="","",CHOOSE(MATCH($C$7,{"Weekly","Every 2 weeks","Twice a month","Monthly"},0),B21+7,B21+14,IF(DAY(B21)<15,DATE(YEAR(B21),MONTH(B21),15),DATE(YEAR(B21),MONTH(B21)+1,1)),EDATE(B21,1)))
B22: =IF(F21="","",IF(F21>DATE(Year,12,31),"",F21)) | C22: =IF(B22="","",$C$8) | D22: =IF(B22="","",SUMPRODUCT(('Bills'!$C$7:$C$31<>"")*(DATE(YEAR(B22),MONTH(B22)+(DAY(B22)>'Bills'!$C$7:$C$31),'Bills'!$C$7:$C$31)<F22)*'Bills'!$D$7:$D$31)) | E22: =IF(B22="","",C22-D22) | F22: =IF(B22="","",CHOOSE(MATCH($C$7,{"Weekly","Every 2 weeks","Twice a month","Monthly"},0),B22+7,B22+14,IF(DAY(B22)<15,DATE(YEAR(B22),MONTH(B22),15),DATE(YEAR(B22),MONTH(B22)+1,1)),EDATE(B22,1)))
B23: =IF(F22="","",IF(F22>DATE(Year,12,31),"",F22)) | C23: =IF(B23="","",$C$8) | D23: =IF(B23="","",SUMPRODUCT(('Bills'!$C$7:$C$31<>"")*(DATE(YEAR(B23),MONTH(B23)+(DAY(B23)>'Bills'!$C$7:$C$31),'Bills'!$C$7:$C$31)<F23)*'Bills'!$D$7:$D$31)) | E23: =IF(B23="","",C23-D23) | F23: =IF(B23="","",CHOOSE(MATCH($C$7,{"Weekly","Every 2 weeks","Twice a month","Monthly"},0),B23+7,B23+14,IF(DAY(B23)<15,DATE(YEAR(B23),MONTH(B23),15),DATE(YEAR(B23),MONTH(B23)+1,1)),EDATE(B23,1)))
... B64: =IF(F63="","",IF(F63>DATE(Year,12,31),"",F63)) | C64: =IF(B64="","",$C$8) | D64: =IF(B64="","",SUMPRODUCT(('Bills'!$C$7:$C$31<>"")*(DATE(YEAR(B64),MONTH(B64)+(DAY(B64)>'Bills'!$C$7:$C$31),'Bills'!$C$7:$C$31)<F64)*'Bills'!$D$7:$D$31)) | E64: =IF(B64="","",C64-D64) | F64: =IF(B64="","",CHOOSE(MATCH($C$7,{"Weekly","Every 2 weeks","Twice a month","Monthly"},0),B64+7,B64+14,IF(DAY(B64)<15,DATE(YEAR(B64),MONTH(B64),15),DATE(YEAR(B64),MONTH(B64)+1,1)),EDATE(B64,1)))

Sheet Debt payoff
B2: Debt payoff
B3: List your debts. The order and timelines update as you pay.
B4: Start here | C4: Dashboard | D4: Setup | E4: Months | F4: Bills | G4: Paycheck | H4: Debt | I4: Savings
B6: Method | C6: Snowball
B7: Extra each month | C7: 100 | D7: Goes to the debt that is first in pay order.
B9: Debt | C9: Balance | D9: Rate (APR) | E9: Minimum | F9: Pay order | G9: Months at minimum | H9: Interest at minimum | I9: Months with extra | J9: Interest saved
B10: Credit card | C10: 2400 | D10: 0.2299 | E10: 75 | F10: =IF(C10="","",IF($C$6="Snowball",COUNTIFS($C$10:$C$19,"<"&C10,$C$10:$C$19,"<>")+1,COUNTIFS($D$10:$D$19,">"&D10,$C$10:$C$19,"<>")+1)) | G10: =IF(OR(C10="",E10=""),"",IFERROR(ROUNDUP(NPER(D10/12,-E10,C10),0),"never: raise the minimum")) | H10: =IF(OR(C10="",E10="",NOT(ISNUMBER(G10))),"",G10*E10-C10) | I10: =IF(OR(C10="",E10="",F10<>1),"",IFERROR(ROUNDUP(NPER(D10/12,-(E10+$C$7),C10),0),"")) | J10: =IF(OR(I10="",NOT(ISNUMBER(H10))),"",MAX(0,H10-(I10*(E10+$C$7)-C10)))
B11: Car loan | C11: 8200 | D11: 0.069 | E11: 210 | F11: =IF(C11="","",IF($C$6="Snowball",COUNTIFS($C$10:$C$19,"<"&C11,$C$10:$C$19,"<>")+1,COUNTIFS($D$10:$D$19,">"&D11,$C$10:$C$19,"<>")+1)) | G11: =IF(OR(C11="",E11=""),"",IFERROR(ROUNDUP(NPER(D11/12,-E11,C11),0),"never: raise the minimum")) | H11: =IF(OR(C11="",E11="",NOT(ISNUMBER(G11))),"",G11*E11-C11) | I11: =IF(OR(C11="",E11="",F11<>1),"",IFERROR(ROUNDUP(NPER(D11/12,-(E11+$C$7),C11),0),"")) | J11: =IF(OR(I11="",NOT(ISNUMBER(H11))),"",MAX(0,H11-(I11*(E11+$C$7)-C11)))
B12: Student loan | C12: 14500 | D12: 0.055 | E12: 180 | F12: =IF(C12="","",IF($C$6="Snowball",COUNTIFS($C$10:$C$19,"<"&C12,$C$10:$C$19,"<>")+1,COUNTIFS($D$10:$D$19,">"&D12,$C$10:$C$19,"<>")+1)) | G12: =IF(OR(C12="",E12=""),"",IFERROR(ROUNDUP(NPER(D12/12,-E12,C12),0),"never: raise the minimum")) | H12: =IF(OR(C12="",E12="",NOT(ISNUMBER(G12))),"",G12*E12-C12) | I12: =IF(OR(C12="",E12="",F12<>1),"",IFERROR(ROUNDUP(NPER(D12/12,-(E12+$C$7),C12),0),"")) | J12: =IF(OR(I12="",NOT(ISNUMBER(H12))),"",MAX(0,H12-(I12*(E12+$C$7)-C12)))
F13: =IF(C13="","",IF($C$6="Snowball",COUNTIFS($C$10:$C$19,"<"&C13,$C$10:$C$19,"<>")+1,COUNTIFS($D$10:$D$19,">"&D13,$C$10:$C$19,"<>")+1)) | G13: =IF(OR(C13="",E13=""),"",IFERROR(ROUNDUP(NPER(D13/12,-E13,C13),0),"never: raise the minimum")) | H13: =IF(OR(C13="",E13="",NOT(ISNUMBER(G13))),"",G13*E13-C13) | I13: =IF(OR(C13="",E13="",F13<>1),"",IFERROR(ROUNDUP(NPER(D13/12,-(E13+$C$7),C13),0),"")) | J13: =IF(OR(I13="",NOT(ISNUMBER(H13))),"",MAX(0,H13-(I13*(E13+$C$7)-C13)))
F14: =IF(C14="","",IF($C$6="Snowball",COUNTIFS($C$10:$C$19,"<"&C14,$C$10:$C$19,"<>")+1,COUNTIFS($D$10:$D$19,">"&D14,$C$10:$C$19,"<>")+1)) | G14: =IF(OR(C14="",E14=""),"",IFERROR(ROUNDUP(NPER(D14/12,-E14,C14),0),"never: raise the minimum")) | H14: =IF(OR(C14="",E14="",NOT(ISNUMBER(G14))),"",G14*E14-C14) | I14: =IF(OR(C14="",E14="",F14<>1),"",IFERROR(ROUNDUP(NPER(D14/12,-(E14+$C$7),C14),0),"")) | J14: =IF(OR(I14="",NOT(ISNUMBER(H14))),"",MAX(0,H14-(I14*(E14+$C$7)-C14)))
F15: =IF(C15="","",IF($C$6="Snowball",COUNTIFS($C$10:$C$19,"<"&C15,$C$10:$C$19,"<>")+1,COUNTIFS($D$10:$D$19,">"&D15,$C$10:$C$19,"<>")+1)) | G15: =IF(OR(C15="",E15=""),"",IFERROR(ROUNDUP(NPER(D15/12,-E15,C15),0),"never: raise the minimum")) | H15: =IF(OR(C15="",E15="",NOT(ISNUMBER(G15))),"",G15*E15-C15) | I15: =IF(OR(C15="",E15="",F15<>1),"",IFERROR(ROUNDUP(NPER(D15/12,-(E15+$C$7),C15),0),"")) | J15: =IF(OR(I15="",NOT(ISNUMBER(H15))),"",MAX(0,H15-(I15*(E15+$C$7)-C15)))
F16: =IF(C16="","",IF($C$6="Snowball",COUNTIFS($C$10:$C$19,"<"&C16,$C$10:$C$19,"<>")+1,COUNTIFS($D$10:$D$19,">"&D16,$C$10:$C$19,"<>")+1)) | G16: =IF(OR(C16="",E16=""),"",IFERROR(ROUNDUP(NPER(D16/12,-E16,C16),0),"never: raise the minimum")) | H16: =IF(OR(C16="",E16="",NOT(ISNUMBER(G16))),"",G16*E16-C16) | I16: =IF(OR(C16="",E16="",F16<>1),"",IFERROR(ROUNDUP(NPER(D16/12,-(E16+$C$7),C16),0),"")) | J16: =IF(OR(I16="",NOT(ISNUMBER(H16))),"",MAX(0,H16-(I16*(E16+$C$7)-C16)))
F17: =IF(C17="","",IF($C$6="Snowball",COUNTIFS($C$10:$C$19,"<"&C17,$C$10:$C$19,"<>")+1,COUNTIFS($D$10:$D$19,">"&D17,$C$10:$C$19,"<>")+1)) | G17: =IF(OR(C17="",E17=""),"",IFERROR(ROUNDUP(NPER(D17/12,-E17,C17),0),"never: raise the minimum")) | H17: =IF(OR(C17="",E17="",NOT(ISNUMBER(G17))),"",G17*E17-C17) | I17: =IF(OR(C17="",E17="",F17<>1),"",IFERROR(ROUNDUP(NPER(D17/12,-(E17+$C$7),C17),0),"")) | J17: =IF(OR(I17="",NOT(ISNUMBER(H17))),"",MAX(0,H17-(I17*(E17+$C$7)-C17)))
F18: =IF(C18="","",IF($C$6="Snowball",COUNTIFS($C$10:$C$19,"<"&C18,$C$10:$C$19,"<>")+1,COUNTIFS($D$10:$D$19,">"&D18,$C$10:$C$19,"<>")+1)) | G18: =IF(OR(C18="",E18=""),"",IFERROR(ROUNDUP(NPER(D18/12,-E18,C18),0),"never: raise the minimum")) | H18: =IF(OR(C18="",E18="",NOT(ISNUMBER(G18))),"",G18*E18-C18) | I18: =IF(OR(C18="",E18="",F18<>1),"",IFERROR(ROUNDUP(NPER(D18/12,-(E18+$C$7),C18),0),"")) | J18: =IF(OR(I18="",NOT(ISNUMBER(H18))),"",MAX(0,H18-(I18*(E18+$C$7)-C18)))
F19: =IF(C19="","",IF($C$6="Snowball",COUNTIFS($C$10:$C$19,"<"&C19,$C$10:$C$19,"<>")+1,COUNTIFS($D$10:$D$19,">"&D19,$C$10:$C$19,"<>")+1)) | G19: =IF(OR(C19="",E19=""),"",IFERROR(ROUNDUP(NPER(D19/12,-E19,C19),0),"never: raise the minimum")) | H19: =IF(OR(C19="",E19="",NOT(ISNUMBER(G19))),"",G19*E19-C19) | I19: =IF(OR(C19="",E19="",F19<>1),"",IFERROR(ROUNDUP(NPER(D19/12,-(E19+$C$7),C19),0),"")) | J19: =IF(OR(I19="",NOT(ISNUMBER(H19))),"",MAX(0,H19-(I19*(E19+$C$7)-C19)))
B20: Total | C20: =SUM(C10:C19) | E20: =SUM(E10:E19)

Sheet Savings goals
B2: Savings goals
B3: One line per goal. The bar fills as you save.
B4: Start here | C4: Dashboard | D4: Setup | E4: Months | F4: Bills | G4: Paycheck | H4: Debt | I4: Savings
B6: Goal | C6: Target | D6: Saved | E6: Progress | F6: Target date | G6: Save per month
B7: Emergency fund | C7: 5000 | D7: 1200 | E7: =IF(OR(C7="",C7=0),"",MIN(1,D7/C7)) | F7: 46722 | G7: =IF(OR(C7="",F7=""),"",IF(D7>=C7,"Reached",IF(((YEAR(F7)-YEAR(TODAY()))*12+MONTH(F7)-MONTH(TODAY()))<1,"Date passed: pick a new one",(C7-D7)/((YEAR(F7)-YEAR(TODAY()))*12+MONTH(F7)-MONTH(TODAY()))))) | H7: =IF(E7="","",REPT("█",ROUND(MIN(1,MAX(0,E7))*10,0))&REPT("░",10-ROUND(MIN(1,MAX(0,E7))*10,0)))
B8: Holiday trip | C8: 1800 | D8: 450 | E8: =IF(OR(C8="",C8=0),"",MIN(1,D8/C8)) | F8: 46569 | G8: =IF(OR(C8="",F8=""),"",IF(D8>=C8,"Reached",IF(((YEAR(F8)-YEAR(TODAY()))*12+MONTH(F8)-MONTH(TODAY()))<1,"Date passed: pick a new one",(C8-D8)/((YEAR(F8)-YEAR(TODAY()))*12+MONTH(F8)-MONTH(TODAY()))))) | H8: =IF(E8="","",REPT("█",ROUND(MIN(1,MAX(0,E8))*10,0))&REPT("░",10-ROUND(MIN(1,MAX(0,E8))*10,0)))
B9: New laptop | C9: 1200 | D9: 300 | E9: =IF(OR(C9="",C9=0),"",MIN(1,D9/C9)) | F9: 46631 | G9: =IF(OR(C9="",F9=""),"",IF(D9>=C9,"Reached",IF(((YEAR(F9)-YEAR(TODAY()))*12+MONTH(F9)-MONTH(TODAY()))<1,"Date passed: pick a new one",(C9-D9)/((YEAR(F9)-YEAR(TODAY()))*12+MONTH(F9)-MONTH(TODAY()))))) | H9: =IF(E9="","",REPT("█",ROUND(MIN(1,MAX(0,E9))*10,0))&REPT("░",10-ROUND(MIN(1,MAX(0,E9))*10,0)))
E10: =IF(OR(C10="",C10=0),"",MIN(1,D10/C10)) | G10: =IF(OR(C10="",F10=""),"",IF(D10>=C10,"Reached",IF(((YEAR(F10)-YEAR(TODAY()))*12+MONTH(F10)-MONTH(TODAY()))<1,"Date passed: pick a new one",(C10-D10)/((YEAR(F10)-YEAR(TODAY()))*12+MONTH(F10)-MONTH(TODAY()))))) | H10: =IF(E10="","",REPT("█",ROUND(MIN(1,MAX(0,E10))*10,0))&REPT("░",10-ROUND(MIN(1,MAX(0,E10))*10,0)))
E11: =IF(OR(C11="",C11=0),"",MIN(1,D11/C11)) | G11: =IF(OR(C11="",F11=""),"",IF(D11>=C11,"Reached",IF(((YEAR(F11)-YEAR(TODAY()))*12+MONTH(F11)-MONTH(TODAY()))<1,"Date passed: pick a new one",(C11-D11)/((YEAR(F11)-YEAR(TODAY()))*12+MONTH(F11)-MONTH(TODAY()))))) | H11: =IF(E11="","",REPT("█",ROUND(MIN(1,MAX(0,E11))*10,0))&REPT("░",10-ROUND(MIN(1,MAX(0,E11))*10,0)))
E12: =IF(OR(C12="",C12=0),"",MIN(1,D12/C12)) | G12: =IF(OR(C12="",F12=""),"",IF(D12>=C12,"Reached",IF(((YEAR(F12)-YEAR(TODAY()))*12+MONTH(F12)-MONTH(TODAY()))<1,"Date passed: pick a new one",(C12-D12)/((YEAR(F12)-YEAR(TODAY()))*12+MONTH(F12)-MONTH(TODAY()))))) | H12: =IF(E12="","",REPT("█",ROUND(MIN(1,MAX(0,E12))*10,0))&REPT("░",10-ROUND(MIN(1,MAX(0,E12))*10,0)))
E13: =IF(OR(C13="",C13=0),"",MIN(1,D13/C13)) | G13: =IF(OR(C13="",F13=""),"",IF(D13>=C13,"Reached",IF(((YEAR(F13)-YEAR(TODAY()))*12+MONTH(F13)-MONTH(TODAY()))<1,"Date passed: pick a new one",(C13-D13)/((YEAR(F13)-YEAR(TODAY()))*12+MONTH(F13)-MONTH(TODAY()))))) | H13: =IF(E13="","",REPT("█",ROUND(MIN(1,MAX(0,E13))*10,0))&REPT("░",10-ROUND(MIN(1,MAX(0,E13))*10,0)))
E14: =IF(OR(C14="",C14=0),"",MIN(1,D14/C14)) | G14: =IF(OR(C14="",F14=""),"",IF(D14>=C14,"Reached",IF(((YEAR(F14)-YEAR(TODAY()))*12+MONTH(F14)-MONTH(TODAY()))<1,"Date passed: pick a new one",(C14-D14)/((YEAR(F14)-YEAR(TODAY()))*12+MONTH(F14)-MONTH(TODAY()))))) | H14: =IF(E14="","",REPT("█",ROUND(MIN(1,MAX(0,E14))*10,0))&REPT("░",10-ROUND(MIN(1,MAX(0,E14))*10,0)))
E15: =IF(OR(C15="",C15=0),"",MIN(1,D15/C15)) | G15: =IF(OR(C15="",F15=""),"",IF(D15>=C15,"Reached",IF(((YEAR(F15)-YEAR(TODAY()))*12+MONTH(F15)-MONTH(TODAY()))<1,"Date passed: pick a new one",(C15-D15)/((YEAR(F15)-YEAR(TODAY()))*12+MONTH(F15)-MONTH(TODAY()))))) | H15: =IF(E15="","",REPT("█",ROUND(MIN(1,MAX(0,E15))*10,0))&REPT("░",10-ROUND(MIN(1,MAX(0,E15))*10,0)))
E16: =IF(OR(C16="",C16=0),"",MIN(1,D16/C16)) | G16: =IF(OR(C16="",F16=""),"",IF(D16>=C16,"Reached",IF(((YEAR(F16)-YEAR(TODAY()))*12+MONTH(F16)-MONTH(TODAY()))<1,"Date passed: pick a new one",(C16-D16)/((YEAR(F16)-YEAR(TODAY()))*12+MONTH(F16)-MONTH(TODAY()))))) | H16: =IF(E16="","",REPT("█",ROUND(MIN(1,MAX(0,E16))*10,0))&REPT("░",10-ROUND(MIN(1,MAX(0,E16))*10,0)))
